Workbook

Sheet Start here
A1: Mada Trips · Social Media Plan · November 2026
A2: Instagram · TikTok · X · LinkedIn. Researched 18 Oct 2026. Times are Riyadh (AST, UTC+3).
A4: Situation | B4: Mada is a new account on every platform. Month one sets up the profiles, the recurring series that make us recognisable, and the habit of posting daily.
B5: Riyadh's airport (RUH) was hit by Houthi missiles and drones several times in early-mid October 2026 and reopened on 18 Oct. Several foreign airlines are still suspended into November (Lufthansa to 18 Nov, KLM to 31 Oct, BA limited from 3 Nov). The plan leads with domestic and short-haul trips, Riyadh Season, practical help and calm reassurance. There are no airport jokes and no 'fly now' hype. See the sensitivity protocol.
B6: Several big December events were cancelled or moved this season (Red Sea Film Festival postponed to 2027, MDLBEAST Soundstorm 2026 cancelled, Formula E moved from Diriyah to Jeddah, Six Kings Slam moved to 27-30 Dec). Re-check every event date the week it is posted.
B7: The calendar's biggest commercial moments are the school autumn break (20-28 Nov), White Friday (27 Nov), and Rajab (from ~10 Dec), which opens Umrah planning for Ramadan 1448 (~8 Feb 2027).
A9: Objectives | B9: Be found: Rank in TikTok and Instagram search for high-intent Arabic travel and visa terms (تأشيرة شنغن, إجازة الخريف, العلا, باقات عمرة).
B10: Be remembered: Make 4-5 named series that people recognise and follow: One Call, Visa in 60, Weekend Radar, Concierge Confessions, Behind the Curtain.
B11: Be trusted: Show the people behind the service. No Saudi OTA puts a real advisor on camera, and that is our white space.
B12: Convert: Move intent to WhatsApp: every post has one CTA, and every DM gets an answer within the hour during working hours.
A14: How to use this file | B14: Calendar: every post with its hook, poster text (EN/AR), caption (AR/EN), keywords, hashtags, CTA and production direction. Filter by platform, week or pillar.
B15: Fill in Owner and Status for each post. The Status dropdown runs Idea → Scripted → Shot → Designed → Approved → Scheduled → Posted (or Paused).
B16: After posting, fill the yellow results columns (Reach … Saves). The engagement rate calculates itself, and 'KPIs & tracking' rolls it up by platform.
B17: Rows flagged in the Notes column (OFFER, APPROVAL, SENSITIVITY) can't be scheduled without that sign-off.
B18: Month view: the whole month at a glance. Guidelines, Keywords, Competitors and Moments hold the research behind every post.
A20: Posts this month
A21: Platform | B21: Posts (counted from Calendar)
A22: Instagram | B22: =COUNTIF(Calendar!$E:$E,"Instagram") -> 35
A23: TikTok | B23: =COUNTIF(Calendar!$E:$E,"TikTok") -> 34
A24: X | B24: =COUNTIF(Calendar!$E:$E,"X") -> 30
A25: LinkedIn | B25: =COUNTIF(Calendar!$E:$E,"LinkedIn") -> 12
A26: Total | B26: =SUM(B22:B25) -> 111

Sheet Calendar
A1: # | B1: Date | C1: Day | D1: Time (AST) | E1: Platform | F1: Format | G1: Pillar | H1: Series | I1: Moment / trend | J1: Working title | K1: Hook (first 1-3s / first line) | L1: On-poster / on-screen text (EN) | M1: On-poster / on-screen text (AR) | N1: Caption / copy (AR) | O1: Caption / copy (EN) | P1: Search keywords | Q1: Hashtags (max 5) | R1: CTA | S1: Visual / audio / production direction | T1: Notes · approvals · risks | U1: Owner | V1: Status | W1: Reach | X1: Views | Y1: Likes | Z1: Comments | AA1: Shares | AB1: Saves | AC1: Eng. rate
A2: 1 | B2: 46327 | C2: Sun | D2: 20:30 | E2: Instagram | F2: Reel 30s | G2: Moments & Offers | I2: Brand launch | J2: Launch film: Every horizon, within reach | K2: Black screen, one word in gold: مدى / Reach | L2: Every horizon, within reach. | M2: كل أفق، في متناولك. | N2: مادا يعني المدى. ومن اليوم، رحلتك وفعاليتك وفريقك… كلها بمكالمة وحدة. تذاكر، فنادق، تأشيرات، فعاليات، كوادر وتقنية — من الرياض لكل أفق. تابعنا، القادم أجمل 🌙 | O2: Mada is Arabic for reach. Flights, stays, visas, events, crews and tech. From Riyadh to every horizon. One call. Everything moves. | P2: وكالة سفر الرياض, Riyadh travel agency, مادا للسفر | Q2: #مادا #MadaTrips #الرياض #سفر #RiyadhTravel | R2: Follow + tap the WhatsApp button in bio | S2: Cinematic 6-scene cut, 4-5s each: dunes at sunrise → boarding gate → hotel door opening to a ready room → stage lights warming up → concierge answering a phone at 03:00 → logo resolve. Calm Najdi VO (male or female). Warm sand/green grade. Ambient oud with a slow rise. Burned-in Arabic subtitles + English. | T2: PIN to profile. Shoot original footage only (Instagram stops recommending reposted clips since Apr 2026). | V2: Scripted | AC2: =IF(OR(W2="",W2=0),"",(Y2+Z2+AA2+AB2)/W2)
A3: 2 | B3: 46327 | C3: Sun | D3: 21:00 | E3: TikTok | F3: Video 20s | G3: One Call | I3: Brand launch | J3: POV: you said it once and it just happened | K3: On-screen: لما تقول طلبك مرة وحدة… 👀 | L3: You said it once. We did the rest. | M3: قلتها مرة… والباقي علينا | N3: أول فيديو لنا 👋 احنا مادا من الرياض. قل طلبك مرة، والباقي علينا ✈️🏨 وش أول وجهة نخطط لها لك؟ اكتبها بالتعليقات 👇 | O3: Our first video. We're Mada from Riyadh. Say it once and we handle the rest. Where should we plan first? Comment below. | P3: تخطيط رحلة, رحلة العلا, travel planner Riyadh | Q3: #مادا #سفر #العلا #السعودية #tiktoksaudi | R3: Comment your dream destination | S3: Open on a real-sounding voice note bubble: 'أبي آخذ أهلي العلا الويكند الجاي'. Jump cuts in sync with a trending beat: laptop, WhatsApp confirmations popping (flight ✓ hotel ✓ transfer ✓), then the family (from behind) walking into Hegra at golden hour. 9:16, captions on. | T3: Reply to every comment with a video reply over the following days. That reply series feeds week 2. | V3: Scripted | AC3: =IF(OR(W3="",W3=0),"",(Y3+Z3+AA3+AB3)/W3)
A4: 3 | B4: 46327 | C4: Sun | D4: 13:00 | E4: X | F4: Post (pinned) | G4: Moments & Offers | I4: Brand launch | J4: Launch post | K4: مادا يعني المدى. | N4: مادا يعني المدى. من اليوم، كل أفق في متناولك: سفر، تذاكر، فنادق، تأشيرات، فعاليات، كوادر وتقنية. فريق واحد يرد عليك حتى الساعة ٣ الفجر. وش الوجهة اللي تحلم فيها هالشتاء؟ 👇 | O4: Mada means reach. From today every horizon is within reach: travel, tickets, hotels, visas, events, crews and tech. One team that picks up even at 3 a.m. Where are you dreaming of this winter? | P4: وكالة سفر, سفر الشتاء | Q4: #مادا | R4: Reply with a destination | S4: Attach the launch film's 15s cut (native upload, not a link). | T4: Pin. Reply to every answer within the hour, since replies feed ranking. | V4: Scripted | AC4: =IF(OR(W4="",W4=0),"",(Y4+Z4+AA4+AB4)/W4)
A5: 4 | B5: 46327 | C5: Sun | D5: 09:30 | E5: LinkedIn | F5: Image + post | G5: Events & Business | I5: Brand launch | J5: Mada Trips opens its doors | K5: One partner for everything that moves. | L5: One partner for everything that moves. | M5: شريك واحد لكل ما يتحرك | O5: Today Mada Trips opens its doors in Riyadh. Most organisations juggle seven vendors to move one delegation: an airline desk, a hotel contact, a visa agent, an event producer, a crew supplier, an IT vendor and someone who chases them all. We built Mada so that is one call. → Travel, ticketing and hotels → Visa support and business services → Manpower and specialist supply → Events and the IT beneath them One team, one point of contact, one report that accounts for every riyal. If you are planning a delegation, a conference or a project mobilisation for 2027, we'd like to hear about it. | P5: corporate travel Saudi Arabia, event management Riyadh, manpower supply KSA | Q5: #Riyadh #CorporateTravel #EventManagement #Vision2030 | R5: Message us / visit the website | S5: Single 1200x1500 image: sand background, green headline, the 9 service names in a quiet grid, symbol in gold. Founder reshares with a personal line within 2 hours. | T5: Ask the founder and every team member to comment with substance (not 'congrats') in the first hour. | V5: Scripted | AC5: =IF(OR(W5="",W5=0),"",(Y5+Z5+AA5+AB5)/W5)
A6: 5 | B6: 46328 | C6: Mon | D6: 20:30 | E6: Instagram | F6: Carousel 10 | G6: One Call | I6: Launch week | J6: 9 services. 1 call. | K6: Slide 1: Say it once. We'll take it from there. | L6: Say it once. We'll take it from there. | M6: قلها مرة… ونكمّل عنك | N6: تسع خدمات، ورقم واحد. ١ السفر ٢ التذاكر ٣ الفنادق ٤ التأشيرات ٥ خدمات الأعمال ٦ الكوادر ٧ المختصين ٨ الفعاليات ٩ الحلول التقنية احفظ المنشور لين تحتاجنا 📌 | O6: Nine services, one number. Travel, ticketing, hotels, visas, business services, manpower, specialists, events, IT. Save this for when you need us. | P6: خدمات سفر, حجز فنادق, تأشيرات, تنظيم فعاليات | Q6: #مادا #MadaTrips #خدمات_سفر #تنظيم_فعاليات #الرياض | R6: Save + share with the person who always plans | S6: 4:5 (1080x1350). One service per slide: a single real photo, a 3-word promise, the Arabic word large in Reem Kufi. Slide 10: WhatsApp number + 'One call. Everything moves.' Keep text off the bottom 300px. | V6: Scripted | AC6: =IF(OR(W6="",W6=0),"",(Y6+Z6+AA6+AB6)/W6)
A7: 6 | B7: 46328 | C7: Mon | D7: 21:00 | E7: TikTok | F7: Video 50s | G7: Know Before You Go | H7: Visa in 60 | I7: Evergreen visa (rule since Apr 2024) | J7: Schengen 5-year visa for Saudis | K7: Spoken + on-screen in the first 2s: فيزا شنغن ٥ سنوات؟ حتى من أول مرة! | L7: 5-year Schengen. Even on your first application. | M7: شنغن ٥ سنوات… حتى من أول مرة | N7: فيزا شنغن متعددة لين ٥ سنوات للسعوديين المقيمين في المملكة — حتى لو أول مرة تقدم ✅ بس فيه ٣ أشياء لازم تعرفها قبل الموعد 👇 احفظ الفيديو وأرسله لرفيق السفر. | O7: Saudi nationals living in the Kingdom can get a multiple-entry Schengen visa of up to 5 years, even on a first application. Here are 3 things to know before your appointment. | P7: تأشيرة شنغن, فيزا شنغن للسعوديين, شنغن ٥ سنوات, Schengen visa Saudi | Q7: #تأشيرة_شنغن #فيزا #سفر #السعودية #مادا | R7: Save + 'send to your travel buddy' | S7: Concierge on camera, green-screen behind with the EU visa page. 3 numbered points as text pops: (1) validity is at the embassy's discretion, (2) apply 3-6 weeks before travel, (3) bring bank statement + employment letter + insurance. End card: 'Want us to prepare your file? Link in bio'. | T7: Legal check: say 'up to' and 'at the embassy's discretion'. Never promise approval. | V7: Scripted | AC7: =IF(OR(W7="",W7=0),"",(Y7+Z7+AA7+AB7)/W7)
A8: 7 | B8: 46328 | C8: Mon | D8: 12:30 | E8: X | F8: Thread 5 | G8: Know Before You Go | H8: Visa in 60 | I8: Evergreen visa | J8: Schengen 5-year visa thread | K8: فيزا شنغن ٥ سنوات للسعوديين: الدليل المختصر 🧵 | N8: ١/ فيزا شنغن متعددة لين ٥ سنوات للسعوديين المقيمين بالمملكة، حتى في أول طلب. الدليل المختصر 🧵 ٢/ المدة تقررها السفارة حسب ملفك. السفر السابق والملف المرتب يفرقون. ٣/ قدّم قبل سفرك بـ٣ إلى ٦ أسابيع، ولا تقدم قبل أكثر من ٦ شهور. ٤/ الأساسيات: جواز ساري، كشف حساب، خطاب جهة العمل، تأمين سفر، حجوزات. ٥/ تبي نجهز ملفك ونحجز موعدك؟ نسويها لك من البداية للنهاية. | O8: 1/ Saudis living in KSA can get a multiple-entry Schengen visa of up to 5 years, even on a first application. 2/ The embassy decides the validity. 3/ Apply 3-6 weeks before travel, never more than 6 months. 4/ Basics: passport, bank statement, employer letter, insurance, bookings. 5/ Want us to prepare your file? | P8: تأشيرة شنغن, Schengen visa | Q8: #تأشيرة_شنغن | R8: DM / WhatsApp | S8: Text-only thread (text posts carry the highest median engagement on X per Buffer 2026). One image on tweet 1: a branded checklist card. | T8: Space threads at least 3 hours from other posts. X downranks bursts from the same author. | V8: Scripted | AC8: =IF(OR(W8="",W8=0),"",(Y8+Z8+AA8+AB8)/W8)
A9: 8 | B9: 46329 | C9: Tue | D9: 20:30 | E9: Instagram | F9: Static 4:5 | G9: Moments & Offers | I9: Launch week | J9: A note from our founder | K9: In Arabia, no guest walks alone. | L9: “In Arabia, no guest walks alone.” Bader Al Sulaiman | M9: «في جزيرة العرب، ما يمشي ضيف وحده.» بدر السليمان | N9: في جزيرة العرب، ما يمشي ضيف وحده. هذا الوعد اللي بنينا عليه مادا: كل مسافر، كل فريق، وكل فكرة تجي للمملكة… معها أحد. — بدر السليمان، المؤسس والرئيس التنفيذي | O9: In Arabia, no guest walks alone. That promise is what Mada is built on: every traveller, every team and every idea that comes to the Kingdom has someone with them. Bader Al Sulaiman, Founder & CEO. | P9: مادا, بدر السليمان | Q9: #مادا #MadaTrips #ضيافة #الرياض | R9: Follow for the journey | S9: Founder portrait (assets/img/founder.jpg) in green duotone, quote in Instrument Serif italic EN + Aref Ruqaa AR, signature at bottom. | T9: APPROVAL: the quote is still draft copy (see README). Get Bader's sign-off before scheduling. | V9: Scripted | AC9: =IF(OR(W9="",W9=0),"",(Y9+Z9+AA9+AB9)/W9)
A10: 9 | B10: 46329 | C10: Tue | D10: 21:00 | E10: TikTok | F10: Video 45s | G10: Horizons | I10: Riyadh Season 2026 (from 21 Oct) | J10: 5 things nobody tells you about Riyadh Season | K10: On-screen: ٥ أشياء محد يقولها لك عن موسم الرياض 🤫 | L10: 5 things nobody tells you about Riyadh Season | M10: ٥ أشياء محد يقولها لك عن موسم الرياض | N10: موسم الرياض ٢٠٢٦ بدأ ✨ بس قبل تروح… هذي ٥ أشياء محد يقولها لك 👇 أي وحدة كنت تعرفها؟ | O10: Riyadh Season 2026 is on. Before you go, here are 5 things nobody tells you. Which one did you already know? | P10: موسم الرياض, موسم الرياض ٢٠٢٦, Riyadh Season 2026, بوليفارد وورلد | Q10: #موسم_الرياض #بوليفارد_وورلد #الرياض #RiyadhSeason #مادا | R10: Comment which tip you didn't know | S10: Fast list format, one tip per 7-8s, real footage from Boulevard World and Boulevard City: (1) book tickets ahead on the official app (2) weekdays after 9pm are calmer (3) comfortable shoes, it's a lot of walking (4) agree a meeting point, signal drops in crowds (5) check each zone's opening days. Text + VO. | T10: Verify zone hours on the official channels the morning of posting. | V10: Scripted | AC10: =IF(OR(W10="",W10=0),"",(Y10+Z10+AA10+AB10)/W10)
A11: 10 | B11: 46329 | C11: Tue | D11: 12:00 | E11: X | F11: Post | G11: One Call | I11: Airline schedule changes after the October RUH closures | J11: Disruption help line | K11: رحلتك تأثرت بتعديلات الطيران الأخيرة؟ | N11: رحلتك تأثرت بتعديلات الطيران الأخيرة؟ أرسل لنا رقم الحجز على الواتساب، ونتابع لك خيارات التعديل أو الاسترداد مع شركة الطيران، بدون ما تنتظر على الخط. حتى لو ما حجزت معنا. | O11: Was your flight affected by recent schedule changes? Send us your booking reference on WhatsApp and we'll chase change or refund options with the airline. Even if you didn't book with us. | P11: تعديل رحلة, استرداد تذكرة | R11: WhatsApp | S11: Text only, calm tone. No airport imagery, no mention of attacks. | T11: SENSITIVITY: post only if foreign carriers' suspensions are still affecting travellers that week (check Monday). Never joke about airports or safety. | V11: Scripted | AC11: =IF(OR(W11="",W11=0),"",(Y11+Z11+AA11+AB11)/W11)
A12: 11 | B12: 46329 | C12: Tue | D12: 09:30 | E12: LinkedIn | F12: Document 8 pages | G12: Events & Business | I12: Post-FII10 (26-29 Oct) | J12: Hosting international delegates in Riyadh: the checklist | K12: Page 1: 200 delegates land in Riyadh in 12 weeks. What has to be true? | L12: Hosting delegates in Riyadh: the 2027 checklist | O12: FII10 just wrapped, and 2027's calendar is already filling. If you are hosting international delegates in Riyadh, this is the checklist we run: 1. Visas: business eVisa vs visit visa, lead times per nationality 2. Arrivals: meet-and-assist, fast-track, VIP lanes 3. Rooms: blocks near the venue, release dates, rooming lists 4. Ground: transfer waves timed to sessions, not flights 5. Badging and registration 6. Cultural briefing: dress, prayer times, Friday schedules 7. A single live status board for the host team 8. The after-report: every booking, every riyal Swipe for the full version. Save it for your next event. | P12: delegation management Riyadh, MICE Saudi Arabia, business eVisa Saudi | Q12: #MICE #Riyadh #EventManagement #CorporateTravel | R12: Save + DM 'CHECKLIST' for the editable version | S12: PDF carousel, 1080x1350 pages, sand background, one point per page with a small icon. Documents lead LinkedIn engagement (Buffer 2026, Socialinsider 2026). | V12: Scripted | AC12: =IF(OR(W12="",W12=0),"",(Y12+Z12+AA12+AB12)/W12)
A13: 12 | B13: 46330 | C13: Wed | D13: 20:30 | E13: Instagram | F13: Reel 35s | G13: One Call | H13: One Call | I13: AlUla Skies Festival 6-15 Nov | J13: One Call #1: three rooms for AlUla Skies | K13: Voice note plays: 'نبي ٣ غرف بالعلا ويكند مهرجان السماء…' | L13: One call. 3 rooms. 4 minutes. | M13: مكالمة وحدة. ٣ غرف. ٤ دقائق. | N13: مكالمة وحدة… والويكند جاهز 🎈 سلسلة «مكالمة وحدة»: طلبات حقيقية، وكيف نحلها. وش الطلب اللي تبينا نحله في الحلقة الجاية؟ | O13: One call and the weekend is ready. 'One Call' is our series of real requests and how we solve them. What should we solve next? | P13: مهرجان سماء العلا, فنادق العلا, AlUla Skies Festival | Q13: #مكالمة_وحدة #العلا #سماء_العلا #مادا #AlUla | R13: Comment your request for the next episode | S13: Split screen. Left: the client's voice note waveform + subtitles. Right: the concierge working (calls, screens blurred, confirmations). A running timer top-right. Ends on the client's reply: '😍 تم'. Natural office sound, no music under the voice. | T13: Re-enact with consent and anonymise. Label it 'based on a real request' if re-enacted. | V13: Scripted | AC13: =IF(OR(W13="",W13=0),"",(Y13+Z13+AA13+AB13)/W13)
A14: 13 | B14: 46330 | C14: Wed | D14: 21:00 | E14: TikTok | F14: Video 40s | G14: Horizons | I14: AlUla Skies Festival 6-15 Nov | J14: AlUla Skies Festival: what to do | K14: On-screen + VO: العلا تفتح سماها ٦ نوفمبر 🎈 | L14: AlUla Skies · 6-15 Nov | M14: سماء العلا · ٦–١٥ نوفمبر | N14: مهرجان سماء العلا من ٦ لين ١٥ نوفمبر 🎈🔭 مناطيد الشروق، عروض المناطيد المضيئة بالليل، ورصد النجوم بأظلم ليالي الشهر. مين بتاخذ معك؟ منشنه 👇 | O14: AlUla Skies Festival, 6-15 November: sunrise balloon flights, balloon glow at night and stargazing on the darkest nights of the month. Tag who you're taking. | P14: مهرجان سماء العلا, العلا نوفمبر, منطاد العلا, AlUla Skies | Q14: #العلا #سماء_العلا #منطاد #السعودية #مادا | R14: Tag a friend | S14: Countdown style: 3 beats (balloons at sunrise → balloon glow → stars over the rocks). Use our own AlUla stills/footage. 'Moonless 7-12 Nov' as a pop-up fact. | T14: Confirm the programme (incl. any concert) on Experience AlUla's channels before posting. | V14: Scripted | AC14: =IF(OR(W14="",W14=0),"",(Y14+Z14+AA14+AB14)/W14)
A15: 14 | B15: 46330 | C15: Wed | D15: 18:00 | E15: X | F15: Poll | G15: Horizons | I15: AlUla Skies Festival | J15: AlUla: which one? | K15: في العلا، وش تختار أول؟ | N15: في العلا، وش تختار أول؟ 🏜️ | O15: In AlUla, what do you pick first? | P15: العلا | Q15: #سماء_العلا | R15: Vote | S15: Poll options: 🎈 منطاد الشروق / 🔭 رصد النجوم / 🏛️ جولة الحِجر / 🍽️ عشاء بالصحراء | V15: Scripted | AC15: =IF(OR(W15="",W15=0),"",(Y15+Z15+AA15+AB15)/W15)
A16: 15 | B16: 46331 | C16: Thu | D16: 19:30 | E16: Instagram | F16: Carousel 7 | G16: Horizons | H16: Weekend Radar | I16: Riyadh Season, AlUla Skies, WWE Crown Jewel (7 Nov) | J16: Weekend Radar #1 | K16: Slide 1: This weekend in Riyadh & beyond · 5-7 Nov | L16: Weekend Radar · 5-7 Nov | M16: رادار الويكند · ٥–٧ نوفمبر | N16: رادار الويكند 📡 • موسم الرياض: الأجنحة الجديدة في بوليفارد وورلد (هولندا، البرتغال، اليمن) • العلا: افتتاح مهرجان سماء العلا الجمعة • السبت: ليلة WWE Crown Jewel في الرياض • موسم سباقات الرياض مستمر احفظه وشاركه مع شلتك 📌 | O16: Weekend Radar. Riyadh Season's new Boulevard World pavilions, AlUla Skies opens Friday, WWE Crown Jewel on Saturday, and Riyadh racing season continues. Save and share. | P16: فعاليات الرياض هالويكند, وش اسوي بالرياض, Riyadh this weekend | Q16: #رادار_الويكند #موسم_الرياض #فعاليات_الرياض #الرياض #مادا | R16: Save + share to your group | S16: Recurring template every Thursday: green cover with a radar-sweep graphic, one event per slide with date, place and a one-line tip. Last slide: 'Need tickets, a table or a ride? WhatsApp'. | V16: Scripted | AC16: =IF(OR(W16="",W16=0),"",(Y16+Z16+AA16+AB16)/W16)
A17: 16 | B17: 46331 | C17: Thu | D17: 21:30 | E17: Instagram | F17: Reel 25s | G17: Horizons | I17: AlUla Skies weekend | J17: Pack with me: AlUla in November | K17: Hands open a carry-on: 'AlUla nights are colder than you think' | L17: AlUla in November: pack for two seasons | M17: العلا في نوفمبر: جهز لفصلين | N17: العلا في نوفمبر: النهار دافي والليل بارد 🧥 هذي شنطتنا لثلاث ليالي. وش الشي اللي دايم تنساه؟ | O17: AlUla in November: warm days, cold nights. Here's our bag for 3 nights. What do you always forget? | P17: وش اخذ معي العلا, ملابس العلا, AlUla packing list | Q17: #العلا #شنطة_السفر #سفر #مادا #AlUla | R17: Comment what you always forget | S17: Top-down ASMR packing, no VO. Real sounds (zips, folding). On-screen labels: layers, scarf, walking shoes, power bank, headlamp for stargazing, sunscreen. Last frame: a ready card 'Transfer booked ✓'. | V17: Scripted | AC17: =IF(OR(W17="",W17=0),"",(Y17+Z17+AA17+AB17)/W17)
A18: 17 | B18: 46331 | C18: Thu | D18: 20:00 | E18: TikTok | F18: Video 55s | G18: Horizons | I18: Riyadh Season 2026 | J18: Riyadh Season zones in 60 seconds | K18: VO: موسم الرياض بدقيقة. يلا 🏃 | L18: Riyadh Season in 60s | M18: موسم الرياض بدقيقة | N18: موسم الرياض ٢٠٢٦ بدقيقة ⏱️ وش المنطقة اللي بتبدأ فيها؟ بوليفارد وورلد، بوليفارد سيتي، ونستر غاردن، ذا قروفز، سوق المزارعين، وأنا عربية في ڤيا رياض. | O18: Riyadh Season 2026 in a minute: Boulevard World, Boulevard City, Wonder Garden, The Groves, the Farmers' Market and Ana Arabia at VIA Riyadh. Where do you start? | P18: مناطق موسم الرياض, موسم الرياض ٢٠٢٦, Riyadh Season zones | Q18: #موسم_الرياض #RiyadhSeason #الرياض #فعاليات #مادا | R18: Comment your first zone | S18: Walk-and-talk, one zone per 8s, a location pin pops for each. Keep the zone names on screen for search. | V18: Scripted | AC18: =IF(OR(W18="",W18=0),"",(Y18+Z18+AA18+AB18)/W18)
A19: 18 | B19: 46331 | C19: Thu | D19: 22:00 | E19: TikTok | F19: Photo carousel 6 | G19: Horizons | I19: AlUla Skies | J19: Rate my itinerary: 3 days in AlUla | K19: Slide 1: قيّم برنامجي: ٣ أيام في العلا من ١٠ | L19: Rate my itinerary: AlUla 3 days | M19: قيّم برنامجي: ٣ أيام بالعلا | N19: قيّم برنامجنا من ١٠ 👇 وش تضيف؟ وش تشيل؟ اليوم ١: وصول + غروب عند جبل الفيل اليوم ٢: الحِجر صباحاً + رصد النجوم اليوم ٣: منطاد الشروق + البلدة القديمة | O19: Rate our itinerary out of 10. Day 1: arrival and sunset at Elephant Rock. Day 2: Hegra and stargazing. Day 3: sunrise balloon and the Old Town. | P19: برنامج العلا ٣ ايام, جدول العلا, AlUla itinerary | Q19: #العلا #برنامج_سياحي #سفر #السعودية #مادا | R19: Rate it in comments | S19: TikTok Photo Mode: big readable Arabic text on each slide, one photo per day. Itinerary text on slides is indexed by search. | V19: Scripted | AC19: =IF(OR(W19="",W19=0),"",(Y19+Z19+AA19+AB19)/W19)
A20: 19 | B20: 46331 | C20: Thu | D20: 13:00 | E20: X | F20: Thread 4 | G20: Horizons | H20: Weekend Radar | I20: Weekend | J20: Weekend Radar on X | K20: وش نسوي هالويكند؟ 📡 | N20: وش نسوي هالويكند؟ 📡 رادار مادا: ١/ موسم الرياض: أجنحة جديدة ببوليفارد وورلد (هولندا، البرتغال، اليمن) ٢/ العلا: مهرجان سماء العلا يبدأ الجمعة ٦ نوفمبر ٣/ السبت ٧ نوفمبر: WWE Crown Jewel تبي تذاكر أو حجز أو توصيل؟ كلمنا. | O20: What's on this weekend: Riyadh Season's new pavilions, AlUla Skies opens Friday, WWE Crown Jewel on Saturday. Need tickets, a booking or a ride? Talk to us. | P20: فعاليات الويكند | Q20: #موسم_الرياض | R20: Reply / DM | S20: Image on tweet 1 = cover slide of the IG Weekend Radar. | V20: Scripted | AC20: =IF(OR(W20="",W20=0),"",(Y20+Z20+AA20+AB20)/W20)
A21: 20 | B21: 46332 | C21: Fri | D21: 20:30 | E21: Instagram | F21: Reel 20s | G21: Horizons | I21: AlUla Skies opening day | J21: 06:00 in AlUla (balloon ASMR) | K21: Sound of the burner first, then black → sunrise | L21: 06:00 · AlUla | M21: ٦ الفجر · العلا | N21: ٦ الفجر في العلا 🎈 بدون كلام. ارفع الصوت. | O21: 6 a.m. in AlUla. No words. Sound on. | P21: منطاد العلا, AlUla hot air balloon, سماء العلا | Q21: #العلا #سماء_العلا #منطاد #AlUla #مادا | R21: Share to someone who'd love this | S21: Pure ASMR: burner roar, wind, quiet gasps. Wide sunrise over the sandstone, then a detail of hands on the basket. No music. No text except the time stamp. | T21: Needs our own crew/creator in AlUla 6-8 Nov. Fallback: swap with the 'One Call #1' cut-down. Do not repost festival footage. | V21: Scripted | AC21: =IF(OR(W21="",W21=0),"",(Y21+Z21+AA21+AB21)/W21)
A22: 21 | B22: 46332 | C22: Fri | D22: 21:00 | E22: TikTok | F22: Video 15s | G22: Horizons | I22: AlUla Skies | J22: POV: 6am in AlUla | K22: On-screen: POV: صحيت ٥ الفجر عشان هذا 👇 | L22: POV: woke up at 5am for this | M22: POV: صحيت ٥ الفجر عشان هذا | N22: يستاهل ولا لا؟ 🎈 #سماء_العلا | O22: Worth it or not? | P22: منطاد العلا, POV العلا | Q22: #سماء_العلا #العلا #POV #السعودية #مادا | R22: Comment 'worth it' or 'no' | S22: Sleepy alarm at 05:00 (relatable) → cut to balloon lift-off on the beat. Short loopable edit. | V22: Scripted | AC22: =IF(OR(W22="",W22=0),"",(Y22+Z22+AA22+AB22)/W22)
A23: 22 | B23: 46332 | C23: Fri | D23: 18:30 | E23: X | F23: Post + image | G23: Horizons | I23: AlUla Skies | J23: AlUla Skies opens today | K23: اليوم يبدأ مهرجان سماء العلا 🎈 | N23: اليوم يبدأ مهرجان سماء العلا 🎈 نصيحة من فريقنا: أظلم الليالي من ٧ لين ١٢ نوفمبر. إذا جيت عشان النجوم، هذي ليالينا. | O23: AlUla Skies Festival starts today. Tip from our team: the darkest nights are 7-12 November. If you're coming for the stars, these are the nights. | P23: سماء العلا | Q23: #سماء_العلا | R23: Bookmark | S23: One original night-sky photo. | T23: Post after Maghrib. Avoid the Friday prayer window. | V23: Scripted | AC23: =IF(OR(W23="",W23=0),"",(Y23+Z23+AA23+AB23)/W23)
A24: 23 | B24: 46333 | C24: Sat | D24: 20:00 | E24: Instagram | F24: Carousel 6 | G24: Know Before You Go | I24: WWE Crown Jewel (7 Nov) | J24: Big night in Riyadh: the stress-free plan | K24: Slide 1: Event night in Riyadh? Here's the plan that never fails | L24: Event night in Riyadh: the no-stress plan | M24: ليلة فعالية بالرياض؟ الخطة اللي ما تخذلك | N24: عندك فعالية الليلة؟ 🎟️ الخطة اللي نعطيها عملاءنا: وصول بدري، نقطة التقاء واضحة، عشاء محجوز قبل، وتوصيل جاهز بعد. احفظها لأي ليلة كبيرة. | O24: Got an event tonight? The plan we give our clients: arrive early, agree a meeting point, book dinner before, have your ride ready after. Save it for any big night. | P24: فعاليات الرياض, Crown Jewel Riyadh, حفلات الرياض | Q24: #فعاليات_الرياض #موسم_الرياض #الرياض #مادا #RiyadhSeason | R24: Save | S24: Checklist design, 5 slides with icons + 1 CTA slide. Timeline graphic 18:00 → 00:30. | V24: Scripted | AC24: =IF(OR(W24="",W24=0),"",(Y24+Z24+AA24+AB24)/W24)
A25: 24 | B25: 46333 | C25: Sat | D25: 21:30 | E25: TikTok | F25: Video 20s | G25: Moments & Offers | I25: WWE Crown Jewel night | J25: Riyadh tonight | K25: On-screen: الرياض الليلة 🔥 | L25: Riyadh tonight | M25: الرياض الليلة | N25: الرياض الليلة غير 🔥 وين كنتم؟ | O25: Riyadh tonight hits different. Where were you? | P25: الرياض الليلة, موسم الرياض | Q25: #الرياض #موسم_الرياض #CrownJewel #RiyadhSeason #مادا | R25: Comment where you were | S25: Atmosphere-only edit: crowds, lights, food stalls, the boulevard skyline. No match or arena footage (rights). Trending sound. | T25: No WWE logos or broadcast footage. | V25: Scripted | AC25: =IF(OR(W25="",W25=0),"",(Y25+Z25+AA25+AB25)/W25)
A26: 25 | B26: 46333 | C26: Sat | D26: 19:00 | E26: X | F26: Post | G26: Moments & Offers | I26: WWE Crown Jewel | J26: Crown Jewel night tip | K26: رايح #CrownJewel الليلة؟ | N26: رايح #CrownJewel الليلة؟ 🎟️ ثلاث نصايح: ١) وصل قبل البداية بساعة ٢) اتفق مع ربعك على نقطة التقاء ٣) حدد مكان الركوب للرجعة من الحين. استمتعوا! | O26: Going to Crown Jewel tonight? Arrive an hour early, agree a meeting point, pick your ride-home spot now. Enjoy! | P26: Crown Jewel الرياض | Q26: #CrownJewel | R26: Reply | S26: Text only. | V26: Scripted | AC26: =IF(OR(W26="",W26=0),"",(Y26+Z26+AA26+AB26)/W26)
A27: 26 | B27: 46334 | C27: Sun | D27: 20:30 | E27: Instagram | F27: Reel 40s | G27: One Call | H27: Concierge Confessions | I27: Evergreen | J27: Concierge Confessions #1: the 3am call | K27: Phone lights up at 03:12. 'Hello… Mada?' | L27: 03:12 · a call we'll never forget | M27: ٣:١٢ الفجر · مكالمة ما ننساها | N27: الساعة ٣:١٢ الفجر… واحد من عملاءنا في مطار بعيد، والرحلة ألغيت. هذي القصة كاملة 👇 «من دفتر الكونسيرج»: قصص حقيقية من شغلنا اليومي. | O27: 03:12. A client at a faraway airport, flight cancelled. Here's the whole story. 'Concierge Confessions': real stories from our day-to-day. | P27: كونسيرج سفر, إلغاء رحلة, travel concierge | Q27: #من_دفتر_الكونسيرج #مادا #سفر #MadaTrips #قصص_سفر | R27: Save + follow the series | S27: Storytime, concierge to camera in a dim office, cutaways to a phone screen and a departure board. Calm, human, slightly funny ending. 40s max. | T27: Real story, anonymised, with the client's OK. | V27: Scripted | AC27: =IF(OR(W27="",W27=0),"",(Y27+Z27+AA27+AB27)/W27)
A28: 27 | B28: 46334 | C28: Sun | D28: 21:00 | E28: TikTok | F28: Video 50s | G28: Know Before You Go | H28: Visa in 60 | I28: Winter in London (Winter Wonderland from 19 Nov) | J28: UK ETA for Saudis | K28: On-screen + VO: بريطانيا بدون فيزا؟ إيه، بس لازم هذا 👇 | L28: UK: no visa, but you need an ETA | M28: بريطانيا بدون فيزا… بس لازم ETA | N28: السعوديين يدخلون بريطانيا بالـETA بدل الفيزا 🇬🇧 كيف تطلعها، كم صلاحيتها، ووش الغلط اللي يأخر الموافقة 👇 | O28: Saudis enter the UK with an ETA instead of a visa. How to get it, how long it lasts and the mistake that delays approval. | P28: تأشيرة بريطانيا, ETA بريطانيا للسعوديين, UK ETA Saudi | Q28: #بريطانيا #تأشيرة #لندن #سفر #مادا | R28: Save + send to your London crew | S28: Phone screen-record of the official UK ETA app (no personal data), concierge voice-over. Facts on screen: apply via the official app or gov.uk, multiple entries, valid 2 years or until the passport expires, stays up to 6 months. Fee: show the current gov.uk figure. | T28: Verify the fee on gov.uk/eta the day before. Third-party sources say £20 from Feb 2026. | V28: Scripted | AC28: =IF(OR(W28="",W28=0),"",(Y28+Z28+AA28+AB28)/W28)
A29: 28 | B29: 46334 | C29: Sun | D29: 12:30 | E29: X | F29: Thread 4 | G29: Know Before You Go | H29: Visa in 60 | I29: Evergreen visa | J29: UK ETA thread | K29: مسافر لندن هالشتاء؟ لا تنسى الـETA 🇬🇧🧵 | N29: ١/ مسافر لندن هالشتاء؟ السعوديين يحتاجون ETA مو فيزا 🧵 ٢/ تطلعها من التطبيق الرسمي أو gov.uk، والموافقة عادة سريعة. ٣/ صالحة سنتين أو لين ينتهي الجواز، دخول متعدد، لين ٦ شهور لكل زيارة. ٤/ تأكد إن رقم الجواز نفسه اللي بتسافر فيه، هذا أكثر غلط نشوفه. | O29: 1/ Flying to London this winter? Saudis need an ETA, not a visa. 2/ Apply in the official app or on gov.uk. 3/ Valid 2 years or until the passport expires, multiple entries, up to 6 months per visit. 4/ Make sure it's the passport you'll travel on. That's the most common mistake we see. | P29: ETA بريطانيا | Q29: #بريطانيا | R29: Bookmark | S29: Text thread. | T29: Verify on gov.uk. | V29: Scripted | AC29: =IF(OR(W29="",W29=0),"",(Y29+Z29+AA29+AB29)/W29)
A30: 29 | B30: 46334 | C30: Sun | D30: 09:30 | E30: LinkedIn | F30: Document 10 pages | G30: Events & Business | H30: Field Notes | I30: Evergreen B2B | J30: Field Notes #1: a 200-person delegation, the 12-week timeline | K30: Page 1: Week -12 to Day 0 | L30: 200 delegates. 12 weeks. One plan. | O30: Field Notes #1. What it takes to bring 200 people to Riyadh for a three-day summit. Week -12: brief, budget, dates, room block Week -10: visa matrix by nationality Week -8: flights in waves, transfer plan Week -6: run of show v1, suppliers locked Week -4: rooming list, badges, dietary needs Week -2: rehearsal, transport dry-run Day 0: arrivals desk live, status board open The keynote gets the applause. The timeline gets everyone into the room. What would you add? | P30: delegation management, conference planning Saudi Arabia, MICE Riyadh | Q30: #FieldNotes #MICE #EventPlanning #Riyadh | R30: Comment what you'd add | S30: PDF document, a Gantt-style timeline across pages in brand green and gold. | V30: Scripted | AC30: =IF(OR(W30="",W30=0),"",(Y30+Z30+AA30+AB30)/W30)
A31: 30 | B31: 46335 | C31: Mon | D31: 20:30 | E31: Instagram | F31: Carousel 8 | G31: Horizons | I31: New moon 9 Nov · AlUla Skies | J31: The darkest nights of the year are this week | K31: Slide 1: The darkest sky of November is this week. Here's where to see it. | L31: Darkest skies: 7-12 Nov | M31: أظلم ليالي نوفمبر: ٧–١٢ | N31: هالأسبوع بدون قمر 🌑 يعني أوضح نجوم بالسنة تقريباً. وين تشوفها: العلا، صحراء الرياض بعيد عن الأنوار، وحافة العالم. ونصيحة: الأحد ١٥ نوفمبر ذروة شهب الأسد 🌠 | O31: No moon this week means some of the clearest stars of the year. Where to see them: AlUla, the desert outside Riyadh away from city lights, Edge of the World. And on Sunday 15 Nov the Leonid meteor shower peaks. | P31: رصد النجوم, نجوم العلا, شهب الاسد, stargazing Saudi | Q31: #رصد_النجوم #العلا #شهب_الأسد #السعودية #مادا | R31: Save | S31: Night photography slides, a moon-phase strip graphic on slide 2, map of 3 spots, tips (red light, 20 min for eyes to adjust, warm layers). | V31: Scripted | AC31: =IF(OR(W31="",W31=0),"",(Y31+Z31+AA31+AB31)/W31)
A32: 31 | B32: 46335 | C32: Mon | D32: 21:00 | E32: TikTok | F32: Video 30s | G32: Horizons | I32: New moon 9 Nov | J32: Why tonight is the darkest night | K32: VO: الليلة ما فيه قمر… وهذا خبر حلو 🌑 | L32: No moon tonight. Good news. | M32: الليلة بدون قمر… وهذا خبر حلو | N32: ليش الليالي اللي بدون قمر أحلى للنجوم؟ 🌑✨ وين تشوفها قريب منك؟ | O32: Why moonless nights are best for stars, and where to see them near you. | P32: رصد النجوم الرياض, وين اشوف النجوم | Q32: #رصد_النجوم #الرياض #العلا #السعودية #مادا | R32: Comment your city | S32: Explainer with a simple animation of moon phases, then real stars timelapse. | V32: Scripted | AC32: =IF(OR(W32="",W32=0),"",(Y32+Z32+AA32+AB32)/W32)
A33: 32 | B33: 46335 | C33: Mon | D33: 21:30 | E33: X | F33: Post | G33: Horizons | I33: New moon | J33: Stargazing nudge | K33: الليلة بدون قمر 🌑 | N33: الليلة بدون قمر 🌑 لو تقدر تطلع ساعة برا الرياض بعيد عن الأنوار، ارفع راسك. وصورنا اللي تشوفه وحطه بالرد ✨ | O33: No moon tonight. If you can get an hour outside Riyadh away from the lights, look up. Reply with what you see. | P33: رصد النجوم | Q33: #رصد_النجوم | R33: Reply with a photo (UGC) | S33: Text + one star photo. | V33: Scripted | AC33: =IF(OR(W33="",W33=0),"",(Y33+Z33+AA33+AB33)/W33)
A34: 33 | B34: 46336 | C34: Tue | D34: 20:30 | E34: Instagram | F34: Reel 30s | G34: Events & Business | H34: Behind the Curtain | I34: Evergreen events | J34: Behind the Curtain #1: an event build in 30 seconds | K34: Empty hall → full stage in 3 seconds (timelapse hook) | L34: 36 hours in 30 seconds | M34: ٣٦ ساعة في ٣٠ ثانية | N34: قاعة فاضية… وبعد ٣٦ ساعة صارت ليلة ما تنسى ✨ «خلف الستارة»: كيف تنبني فعالياتنا. | O34: An empty hall, and 36 hours later a night nobody forgets. 'Behind the Curtain': how our events get built. | P34: تنظيم فعاليات الرياض, event management Riyadh, تنظيم حفلات | Q34: #خلف_الستارة #تنظيم_فعاليات #فعاليات_الرياض #مادا #MadaEvents | R34: DM 'EVENT' to plan yours | S34: Locked-off timelapse of a real build (stage, truss, lights, tables), then a 3-second real-time payoff of lights on. Crew in branded tees. A sound design build-up. | T34: Needs our own event footage. If no build this month, shoot a small activation or rehearsal. | V34: Scripted | AC34: =IF(OR(W34="",W34=0),"",(Y34+Z34+AA34+AB34)/W34)
A35: 34 | B35: 46336 | C35: Tue | D35: 21:00 | E35: TikTok | F35: Photo carousel 7 | G35: Horizons | I35: AlUla Skies | J35: What a weekend in AlUla actually costs | K35: Slide 1: كم تكلف ويكند بالعلا فعلياً؟ 💸 | L35: AlUla weekend: the real cost | M35: ويكند العلا: التكلفة الحقيقية | N35: كم تكلف ويكند بالعلا فعلياً؟ فصلناها لك بند بند 👇 الأسعار تقريبية لشخصين، وتتغير حسب الموسم. | O35: What does a weekend in AlUla actually cost? Line by line, for two people, approximate and seasonal. | P35: كم تكلف رحلة العلا, اسعار العلا, AlUla trip cost | Q35: #العلا #ميزانية_السفر #سفر #السعودية #مادا | R35: Comment 'تفاصيل' and we'll DM the plan | S35: Photo Mode, one cost line per slide: flights, stay (2 nights), transfers, Hegra, balloon, dinner. Total on the last slide. Clean and transparent, no luxury flexing. | T35: SALES must fill in real SAR ranges before posting. Keep the tone as transparency, not luxury flexing (GAMR rules, Sep 2025). | V35: Scripted | AC35: =IF(OR(W35="",W35=0),"",(Y35+Z35+AA35+AB35)/W35)
A36: 35 | B36: 46336 | C36: Tue | D36: 13:00 | E36: X | F36: Post | G36: Moments & Offers | I36: 11.11 Singles Day | J36: 11.11 teaser | K36: بكرة ١١.١١ 👀 | N36: بكرة ١١.١١ 👀 عندنا شي صغير لأول ١١ حجز. فعّل التنبيه. | O36: Tomorrow is 11.11. Something small for the first 11 bookings. Turn on notifications. | P36: عروض ١١.١١ | Q36: #١١_١١ | R36: Turn on notifications | S36: Text only. | T36: OFFER needs management approval (see 11 Nov). | V36: Scripted | AC36: =IF(OR(W36="",W36=0),"",(Y36+Z36+AA36+AB36)/W36)
A37: 36 | B37: 46336 | C37: Tue | D37: 09:30 | E37: LinkedIn | F37: Post + image | G37: Events & Business | I37: Evergreen B2B | J37: Hiring skilled crews in KSA: what actually takes time | K37: The welders were ready in 10 days. The paperwork took the rest. | L37: Mobilising skilled crews in KSA: where time goes | O37: Clients often ask why mobilising a skilled crew takes weeks when the people are ready in days. Where the time goes: • Work visas and permits through Qiwa • Medical checks and certification checks • Iqama issuance and site access • Housing, transport and safety induction What shortens it: a clear scope early, documents checked before submission, and one partner who owns every step. Timelines vary by role and nationality. If you are planning a 2027 mobilisation, start the conversation now. | P37: manpower supply Saudi Arabia, skilled workers KSA, Qiwa work visa | Q37: #Manpower #SaudiArabia #Workforce #Qiwa | R37: Message us | S37: One image: an infographic bar showing days per stage (illustrative, labelled as such). | T37: Ops to confirm the process steps match our actual workflow. | V37: Scripted | AC37: =IF(OR(W37="",W37=0),"",(Y37+Z37+AA37+AB37)/W37)
A38: 37 | B38: 46337 | C38: Wed | D38: 20:30 | E38: Instagram | F38: Static 4:5 | G38: Moments & Offers | I38: 11.11 Singles Day / ~1 Jumada II | J38: 11.11: 11 bookings, 11 upgrades | K38: 11.11 · 11 bookings · 11 upgrades | L38: 11.11 · The first 11 bookings get an upgrade on us | M38: ١١.١١ · أول ١١ حجز… الترقية علينا | N38: ١١.١١ ✨ أول ١١ حجز اليوم: ترقية علينا (غرفة أعلى، توصيل خاص، أو تشيك آوت متأخر). بدون أكواد. بس قل «١١» على الواتساب. | O38: 11.11. The first 11 bookings today get an upgrade on us: a better room, a private transfer or late checkout. No codes. Just say '11' on WhatsApp. | P38: عروض ١١.١١, عروض سفر | Q38: #عروض_سفر #١١_١١ #مادا #MadaTrips #الرياض | R38: WhatsApp '11' | S38: Typographic poster: huge '11.11' in gold on green, a short line, symbol. Story version with a countdown sticker. | T38: OFFER: management approval + terms (valid today only, subject to availability). | V38: Scripted | AC38: =IF(OR(W38="",W38=0),"",(Y38+Z38+AA38+AB38)/W38)
A39: 38 | B39: 46337 | C39: Wed | D39: 21:00 | E39: TikTok | F39: Video 20s | G39: Moments & Offers | I39: 11.11 | J39: 11.11: what an 'upgrade' means | K39: On-screen: وش يعني «ترقية» عندنا؟ 👇 | L39: What 'upgrade' means at Mada | M39: وش يعني «ترقية» عندنا | N39: اليوم بس: أول ١١ حجز ياخذون ترقية ✨ قل «١١» على الواتساب. | O39: Today only: the first 11 bookings get an upgrade. Say '11' on WhatsApp. | P39: عروض ١١.١١ | Q39: #١١_١١ #عروض_سفر #سفر #السعودية #مادا | R39: WhatsApp '11' | S39: Three quick reveals: the room view, the private car door, the 'late checkout' sign. Fun, fast. | T39: OFFER approval. | V39: Scripted | AC39: =IF(OR(W39="",W39=0),"",(Y39+Z39+AA39+AB39)/W39)
A40: 39 | B40: 46337 | C40: Wed | D40: 12:00 | E40: X | F40: Post | G40: Moments & Offers | I40: 11.11 | J40: 11.11 live | K40: ١١.١١ بدأ ✨ | N40: ١١.١١ بدأ ✨ أول ١١ حجز اليوم ياخذون ترقية علينا. قل «١١» على الواتساب ‎+966 56 668 2662 | O40: 11.11 is live. The first 11 bookings today get an upgrade. Say '11' on WhatsApp. | P40: عروض ١١.١١ | Q40: #١١_١١ | R40: WhatsApp | S40: Poster image. | T40: Post 'all 11 gone' update once claimed (scarcity proof). | V40: Scripted | AC40: =IF(OR(W40="",W40=0),"",(Y40+Z40+AA40+AB40)/W40)
A41: 40 | B41: 46338 | C41: Thu | D41: 19:30 | E41: Instagram | F41: Carousel 7 | G41: Horizons | H41: Weekend Radar | I41: Weekend | J41: Weekend Radar #2 | K41: Slide 1: Weekend Radar · 12-14 Nov | L41: Weekend Radar · 12-14 Nov | M41: رادار الويكند · ١٢–١٤ نوفمبر | N41: رادار الويكند 📡 • آخر ويكند لمهرجان سماء العلا (لين ١٥ نوفمبر) • موسم الرياض: سهرة بوليفارد سيتي • سباقات الخيل بميدان الملك عبدالعزيز • الأحد ١٥: ذروة شهب الأسد 🌠 | O41: Weekend Radar: the last weekend of AlUla Skies, a night at Boulevard City, racing at King Abdulaziz Racecourse, and the Leonids peak on Sunday 15. | P41: فعاليات الرياض هالويكند, Riyadh this weekend | Q41: #رادار_الويكند #موسم_الرياض #فعاليات_الرياض #الرياض #مادا | R41: Save + share | S41: Weekend Radar template. | V41: Scripted | AC41: =IF(OR(W41="",W41=0),"",(Y41+Z41+AA41+AB41)/W41)
A42: 41 | B42: 46338 | C42: Thu | D42: 21:30 | E42: Instagram | F42: Reel 35s | G42: Horizons | H42: Europe in Winter | I42: Vienna Schönbrunn market from 6 Nov · Rathausplatz ~13 Nov | J42: Vienna in winter: 3 days | K42: Snow falling on a Vienna market + text: 'Europe's winter markets open this week' | L42: Vienna in winter · 3 days | M42: فيينا في الشتاء · ٣ أيام | N42: أسواق الشتاء في أوروبا بدأت تفتح ❄️ أولها فيينا. ٣ أيام: القصور، المقاهي القديمة، والأسواق المضيئة بالليل. سلسلة «شتاء أوروبا» تبدأ اليوم. | O42: Europe's winter markets are opening, starting with Vienna. 3 days: palaces, old cafés and lit-up markets at night. Our 'Europe in Winter' series starts today. | P42: فيينا في الشتاء, سفر أوروبا شتاء, Vienna winter trip | Q42: #فيينا #شتاء_أوروبا #سفر #النمسا #مادا | R42: Save for your winter trip | S42: Itinerary reel: Day 1/2/3 chapters with on-screen times. Halal food tip + a prayer-friendly note (useful for the audience). Licensed or original footage only. | T42: Use licensed stock or creator footage under a Collab post, never reposts. | V42: Scripted | AC42: =IF(OR(W42="",W42=0),"",(Y42+Z42+AA42+AB42)/W42)
A43: 42 | B43: 46338 | C43: Thu | D43: 20:00 | E43: TikTok | F43: Video 50s | G43: Horizons | I43: Europe winter markets | J43: Europe this winter: 5 cities ranked for families | K43: On-screen: رتبنا ٥ مدن أوروبية للشتاء مع العائلة 👨‍👩‍👧 | L43: 5 European winter cities, ranked for families | M43: ٥ مدن أوروبية للشتاء مع العائلة | N43: رتبنا لك ٥ مدن أوروبية للشتاء مع العائلة 🇪🇺❄️ توافقنا ولا لا؟ 👇 | O43: We ranked 5 European cities for a family winter trip. Agree or not? | P43: سفر اوروبا شتاء, افضل مدن اوروبا للعائلات, Europe winter family | Q43: #شتاء_أوروبا #سفر_عائلي #أوروبا #سفر #مادا | R43: Comment your ranking | S43: Tier-list format (a trending structure): Vienna, Prague, Strasbourg, London, Salzburg, with criteria: walkability, halal food, flight time from Riyadh, kid-friendliness. Green-screen. | V43: Scripted | AC43: =IF(OR(W43="",W43=0),"",(Y43+Z43+AA43+AB43)/W43)
A44: 43 | B44: 46338 | C44: Thu | D44: 22:00 | E44: TikTok | F44: Video reply 30s | G44: Know Before You Go | H44: Visa in 60 | I44: Week 1 comments | J44: Reply: how long does a Schengen visa take? | K44: Reply-to-comment sticker on screen | L44: How long does Schengen take? | M44: كم ياخذ فيزا شنغن؟ | N44: رد على سؤالكم: كم ياخذ فيزا شنغن؟ ⏳ | O44: Answering your question: how long does a Schengen visa take? | P44: كم ياخذ فيزا شنغن, مدة تأشيرة شنغن | Q44: #تأشيرة_شنغن #فيزا #سفر #مادا #السعودية | R44: Ask your next question | S44: Use TikTok's 'reply with video' on a real comment from the 2 Nov post. Concierge answers in 30s: up to 15 days standard after the appointment, longer in peak season. Book appointments early. | T44: Pick a real question. If none, use one from DMs (anonymised). | V44: Scripted | AC44: =IF(OR(W44="",W44=0),"",(Y44+Z44+AA44+AB44)/W44)
A45: 44 | B45: 46338 | C45: Thu | D45: 13:00 | E45: X | F45: Thread 6 | G45: Horizons | H45: Europe in Winter | I45: Europe winter | J45: Europe's winter markets 2026: opening dates | K45: أسواق الشتاء في أوروبا ٢٠٢٦: متى تفتح؟ 🧵❄️ | N45: ١/ أسواق الشتاء في أوروبا ٢٠٢٦: متى تفتح؟ 🧵 ٢/ فيينا (قصر شونبرون): من ٦ نوفمبر ٣/ لندن (Winter Wonderland هايد بارك): من ١٩ نوفمبر ٤/ ستراسبورغ: من ٢٦ نوفمبر ٥/ براغ: من آخر نوفمبر ٦/ تبي برنامج كامل مع الفيزا والفنادق؟ كلمنا. | O45: 1/ Europe's winter markets 2026, opening dates. 2/ Vienna (Schönbrunn): from 6 Nov. 3/ London (Hyde Park Winter Wonderland): from 19 Nov. 4/ Strasbourg: from 26 Nov. 5/ Prague: from late Nov. 6/ Want a full plan with visa and hotels? Talk to us. | P45: اسواق اوروبا الشتوية | Q45: #شتاء_أوروبا | R45: Bookmark / DM | S45: Image on tweet 1. | T45: Double-check dates against official market sites. | V45: Scripted | AC45: =IF(OR(W45="",W45=0),"",(Y45+Z45+AA45+AB45)/W45)
A46: 45 | B46: 46338 | C46: Thu | D46: 09:30 | E46: LinkedIn | F46: Post (founder voice) | G46: One Call | I46: Evergreen | J46: Why we answer at 3 a.m. | K46: The most important call we took last month came at 3:12 a.m. | O46: The most important call we took last month came at 3:12 a.m. A client's connection was cancelled at an airport six time zones away. The airline desk was closed. He had a meeting in Riyadh at 10. By 3:40 he had a new route, a lounge and a car waiting at the other end. We don't think of that as heroics. In travel, the moments that matter rarely happen during office hours. So we built a team that doesn't keep office hours. That's the whole idea behind Mada: one call, at any hour, and everything moves. | P46: corporate travel management, travel concierge Riyadh | Q46: #CorporateTravel #CustomerExperience #Riyadh | R46: Follow the page | S46: Post from the founder's profile; the company page reshares. A plain-text post with one candid team photo. | T46: Use a real (anonymised) case. | V46: Scripted | AC46: =IF(OR(W46="",W46=0),"",(Y46+Z46+AA46+AB46)/W46)
A47: 46 | B47: 46339 | C47: Fri | D47: 20:30 | E47: Instagram | F47: Reel 30s | G47: One Call | I47: World Kindness Day (13 Nov) | J47: Small things we do that nobody asks for | K47: On-screen: Things we do that nobody asks for 🤍 | L47: Small things nobody asks for | M47: أشياء صغيرة محد يطلبها | N47: اليوم العالمي للطف 🤍 أشياء صغيرة نسويها بدون ما أحد يطلبها: كرسي متحرك جاهز لأمك عند البوابة، كرت بأوقات الصلاة في غرفتك، شاحن بالسيارة، وكلمة ترحيب بخط اليد. | O47: World Kindness Day. Small things we do without being asked: a wheelchair waiting for your mother at the gate, a prayer-times card in your room, a charger in the car, a handwritten welcome note. | P47: خدمة عملاء, ضيافة, travel concierge | Q47: #اليوم_العالمي_للطف #مادا #ضيافة #MadaTrips #سفر | R47: Share with someone who deserves this treatment | S47: Soft, slow close-ups of each gesture with handwritten-style labels. Piano or oud, gentle. Ends on the 'Horizon Card': a calligraphy welcome card that becomes our signature. | T47: Launches the 'Horizon Card' signature gesture. Ops must actually do it from now on. | V47: Scripted | AC47: =IF(OR(W47="",W47=0),"",(Y47+Z47+AA47+AB47)/W47)
A48: 47 | B48: 46339 | C48: Fri | D48: 21:00 | E48: TikTok | F48: Video 25s | G48: One Call | I48: World Kindness Day | J48: Things we do without being asked | K48: On-screen: أشياء نسويها لعملاءنا… بدون ما يطلبونها 🤍 | L48: Things we do without being asked | M48: نسويها بدون ما تطلبها | N48: أشياء صغيرة… بس تفرق 🤍 وش أكثر شي لطيف صار لك بسفرة؟ | O48: Small things that make a difference. What's the kindest thing that happened to you on a trip? | P48: خدمة عملاء سفر | Q48: #اليوم_العالمي_للطف #سفر #مادا #السعودية #لطف | R48: Comment your story | S48: List format with a trending soft sound, one gesture per 4s. | V48: Scripted | AC48: =IF(OR(W48="",W48=0),"",(Y48+Z48+AA48+AB48)/W48)
A49: 48 | B49: 46339 | C49: Fri | D49: 17:30 | E49: X | F49: Post | G49: Moments & Offers | I49: World Kindness Day | J49: World Kindness Day question | K49: أحلى موقف لطيف صار لك من غريب وأنت مسافر؟ | N49: اليوم العالمي للطف 🤍 وش أحلى موقف لطيف صار لك من شخص غريب وأنت مسافر؟ | O49: World Kindness Day. What's the kindest thing a stranger did for you while travelling? | Q49: #اليوم_العالمي_للطف | R49: Reply | S49: Text only. Quote-post the best replies through the day. | T49: Post after Asr, not during Friday prayer. | V49: Scripted | AC49: =IF(OR(W49="",W49=0),"",(Y49+Z49+AA49+AB49)/W49)
A50: 49 | B50: 46340 | C50: Sat | D50: 20:00 | E50: Instagram | F50: Carousel 8 | G50: Horizons | I50: School autumn break 20-28 Nov | J50: Autumn break: 6 short trips from Riyadh | K50: Slide 1: Autumn break starts 20 Nov. 6 trips that don't need a long flight. | L50: Autumn break · 6 short trips | M50: إجازة الخريف · ٦ رحلات قريبة | N50: إجازة الخريف تبدأ ٢٠ نوفمبر 🍂 ٦ رحلات قريبة من الرياض: العلا · أبها والسودة · جدة · مسقط · باكو · تبليسي احفظ وأرسله لأهلك 📌 | O50: The autumn break starts 20 November. 6 short trips from Riyadh: AlUla, Abha & Soudah, Jeddah, Muscat, Baku, Tbilisi. Save and send to your family. | P50: اجازة الخريف, وين نسافر في الاجازة, رحلات قريبة من الرياض | Q50: #إجازة_الخريف #سفر_عائلي #العلا #أبها #مادا | R50: Save + send to the family group | S50: One destination per slide: real photo, flight/drive time from Riyadh, 'best for' tag (families, couples, nature). Last slide: 'We still have dates. WhatsApp'. | T50: Ops to confirm availability before posting. | V50: Scripted | AC50: =IF(OR(W50="",W50=0),"",(Y50+Z50+AA50+AB50)/W50)
A51: 50 | B51: 46340 | C51: Sat | D51: 21:00 | E51: TikTok | F51: Video 35s | G51: Horizons | I51: Autumn break countdown | J51: Autumn break in 6 days: 5 nearby escapes | K51: On-screen: باقي ٦ أيام على الإجازة ومافي خطة؟ 😅 | L51: 6 days to the break. No plan? | M51: باقي ٦ أيام ومافي خطة؟ | N51: باقي ٦ أيام على إجازة الخريف ومافي خطة؟ 😅 هذي ٥ أماكن قريبة تلحق تحجزها 👇 | O51: 6 days to the autumn break and no plan? Here are 5 nearby places you can still book. | P51: اجازة الخريف ١٤٤٨, وين اسافر في الاجازة القصيرة | Q51: #إجازة_الخريف #سفر #السعودية #وين_نسافر #مادا | R51: Comment 'خطة' for a plan in DM | S51: Relatable opener (a panicked family group chat), then a fast 5-destination list with flight times. | V51: Scripted | AC51: =IF(OR(W51="",W51=0),"",(Y51+Z51+AA51+AB51)/W51)
A52: 51 | B52: 46340 | C52: Sat | D52: 13:00 | E52: X | F52: Post | G52: Horizons | I52: Autumn break | J52: Autumn break countdown | K52: باقي ٦ أيام على إجازة الخريف 🍂 | N52: باقي ٦ أيام على إجازة الخريف 🍂 وين ناوين؟ | O52: 6 days to the autumn break. Where are you heading? | P52: اجازة الخريف | Q52: #إجازة_الخريف | R52: Reply | S52: Text only. | V52: Scripted | AC52: =IF(OR(W52="",W52=0),"",(Y52+Z52+AA52+AB52)/W52)
A53: 52 | B53: 46341 | C53: Sun | D53: 20:30 | E53: Instagram | F53: Reel 25s | G53: Horizons | I53: Leonids peak 15 Nov · AlUla Skies closes | J53: Tonight: the Leonids | K53: A meteor streaks across the frame in second 1 | L53: Tonight: Leonids peak | M53: الليلة: ذروة شهب الأسد | N53: الليلة ذروة شهب الأسد 🌠 لين ٢٠ شهاب بالساعة في السماء الصافية. اطلع بعيد عن أنوار المدينة، وعطي عيونك ٢٠ دقيقة تتعود. | O53: Tonight the Leonid meteor shower peaks, up to about 20 meteors an hour under clear skies. Get away from city lights and give your eyes 20 minutes. | P53: شهب الاسد ٢٠٢٦, رصد الشهب الرياض, Leonids 2026 | Q53: #شهب_الأسد #رصد_النجوم #الرياض #السعودية #مادا | R53: Share with your stargazing friend | S53: Night-sky timelapse (shot on 9-12 Nov) with a red-light campsite. On-screen tips. Quiet ambient sound. | T53: Shoot the timelapse in the moonless window earlier in the week. | V53: Scripted | AC53: =IF(OR(W53="",W53=0),"",(Y53+Z53+AA53+AB53)/W53)
A54: 53 | B54: 46341 | C54: Sun | D54: 21:00 | E54: TikTok | F54: Video 20s | G54: Horizons | I54: Leonids 15 Nov | J54: Where to see the meteors near Riyadh | K54: On-screen: الليلة الشهب 🌠 وين تشوفها قرب الرياض؟ | L54: Meteors tonight. Where near Riyadh? | M54: الشهب الليلة… وين قرب الرياض؟ | N54: الليلة ذروة شهب الأسد 🌠 وين تشوفها قرب الرياض؟ 👇 | O54: The Leonids peak tonight. Where to see them near Riyadh. | P54: وين اشوف الشهب الرياض, شهب الاسد | Q54: #شهب_الأسد #الرياض #رصد_النجوم #كشتة #مادا | R54: Comment if you're going out | S54: Map pop-ups: Edge of the World direction, the desert north of the city, the Thumamah area. Note: go with a group and tell someone your route. | T54: Safety line on screen. | V54: Scripted | AC54: =IF(OR(W54="",W54=0),"",(Y54+Z54+AA54+AB54)/W54)
A55: 54 | B55: 46341 | C55: Sun | D55: 12:00 | E55: X | F55: Post | G55: Horizons | I55: Leonids | J55: Leonids alert | K55: الليلة ذروة شهب الأسد 🌠 | N55: الليلة ذروة شهب الأسد 🌠 أفضل وقت بعد منتصف الليل، بعيد عن أنوار المدينة. شاركونا صوركم بالرد. | O55: The Leonids peak tonight. Best after midnight, away from city lights. Share your photos in the replies. | P55: شهب الاسد | Q55: #شهب_الأسد | R55: Reply with photos | S55: Text + one photo. | V55: Scripted | AC55: =IF(OR(W55="",W55=0),"",(Y55+Z55+AA55+AB55)/W55)
A56: 55 | B56: 46341 | C56: Sun | D56: 09:30 | E56: LinkedIn | F56: Document 6 pages | G56: Events & Business | I56: Cityscape Global 16-19 Nov | J56: Cityscape Global week: visitor logistics | K56: Page 1: Flying in for Cityscape Global (16-19 Nov)? Read this first. | L56: Cityscape Global 2026: the visitor's brief | O56: Cityscape Global opens tomorrow at the Riyadh Exhibition & Convention Centre, Malham (16-19 Nov, 12:00-22:00). If your team is flying in, our brief: • Malham is a drive from central Riyadh, so plan transfers by session, not by hotel • Stay where your evening meetings are • Doors open at noon, so use mornings for meetings • Visitors must be 18+ • Book return transfers for 22:00, when everyone leaves at once Need rooms, cars or a meeting space during the show? We still have capacity. | P56: Cityscape Global 2026, Riyadh exhibition travel, corporate transfers Riyadh | Q56: #CityscapeGlobal #Riyadh #RealEstate #BusinessTravel | R56: DM for rooms or transfers | S56: Short document: map graphic, timeline, tips. Brand colours. | T56: Ops to confirm capacity before 'we still have capacity'. | V56: Scripted | AC56: =IF(OR(W56="",W56=0),"",(Y56+Z56+AA56+AB56)/W56)
A57: 56 | B57: 46342 | C57: Mon | D57: 20:30 | E57: Instagram | F57: Carousel 8 | G57: Know Before You Go | I57: International Day for Tolerance (16 Nov) · Cityscape visitors | J57: Hosting guests from abroad: a Saudi hospitality guide | K57: Slide 1: Guests coming to Saudi? 7 things they'll love to know. | L57: Hosting guests in Saudi: 7 things to tell them | M57: ضيوفك جايين السعودية؟ ٧ أشياء قلها لهم | N57: اليوم الدولي للتسامح 🤝 جايك ضيوف من برا؟ أرسل لهم هذا الدليل: القهوة السعودية، اللبس، أوقات الصلاة، الجمعة، البقشيش، الترحيب، والأكل. (The guide is in English for your guests 👇) | O57: International Day for Tolerance. Guests coming from abroad? Send them this: Saudi coffee, what to wear, prayer times, Fridays, tipping, greetings and food. | P57: Saudi etiquette for visitors, Saudi Arabia travel tips, ضيافة سعودية | Q57: #SaudiArabia #VisitSaudi #ضيافة #مادا #Riyadh | R57: Send to your guests | S57: Bilingual, English-led slides, so Saudi followers can forward them to foreign guests. Warm illustration style: a dallah, a finjan, a prayer-time clock. | V57: Scripted | AC57: =IF(OR(W57="",W57=0),"",(Y57+Z57+AA57+AB57)/W57)
A58: 57 | B58: 46342 | C58: Mon | D58: 21:00 | E58: TikTok | F58: Video 30s (English) | G58: Know Before You Go | I58: Tolerance Day · inbound visitors | J58: Saudi coffee etiquette in 30 seconds | K58: On-screen: Never do THIS with Saudi coffee ☕ (shake gesture) | L58: Saudi coffee: the shake rule | M58: القهوة السعودية: سالفة الهز | N58: Saudi coffee etiquette in 30 seconds ☕ Did you know the shake? / تعرف سالفة هز الفنجال؟ | O58: Saudi coffee etiquette in 30 seconds. Did you know about the shake? | P58: Saudi coffee etiquette, Saudi culture, القهوة السعودية | Q58: #SaudiCoffee #SaudiArabia #Riyadh #القهوة_السعودية #مادا | R58: Follow for more Saudi tips | S58: English-led TikTok for expats and visitors (one a week). The host pours: right hand, small amounts, shake the cup when you're done. A playful tone. | V58: Scripted | AC58: =IF(OR(W58="",W58=0),"",(Y58+Z58+AA58+AB58)/W58)
A59: 58 | B59: 46342 | C59: Mon | D59: 13:00 | E59: X | F59: Thread 4 | G59: Events & Business | I59: Cityscape Global | J59: Cityscape Global: visitor tips | K59: رايح سيتي سكيب جلوبال؟ ٤ نصايح 🧵 | N59: ١/ رايح سيتي سكيب جلوبال (١٦–١٩ نوفمبر، ملهم)؟ ٤ نصايح 🧵 ٢/ الأبواب تفتح ١٢ الظهر، فخل الصباح لاجتماعاتك. ٣/ المعرض بعيد عن وسط الرياض، فاحسب وقت الطريق. ٤/ الكل يطلع ١٠ بالليل، فاحجز رجعتك من بدري. نقدر نرتب لك السيارة. | O59: 1/ Going to Cityscape Global (16-19 Nov, Malham)? 4 tips. 2/ Doors open at noon, so keep mornings for meetings. 3/ It's a drive from central Riyadh. 4/ Everyone leaves at 10pm, so book your ride home early. We can arrange the car. | P59: سيتي سكيب ٢٠٢٦ | Q59: #سيتي_سكيب | R59: DM | S59: Text thread. | V59: Scripted | AC59: =IF(OR(W59="",W59=0),"",(Y59+Z59+AA59+AB59)/W59)
A60: 59 | B60: 46343 | C60: Tue | D60: 20:30 | E60: Instagram | F60: Reel 40s | G60: One Call | H60: One Call | I60: Autumn break | J60: One Call #2: a family of 7, 48 hours to plan | K60: Voice note: 'نبي نسافر الإجازة… سبعة أشخاص… وما حجزنا شي' 😅 | L60: 7 people. 48 hours. Done. | M60: ٧ أشخاص. ٤٨ ساعة. تم. | N60: عائلة من ٧ أشخاص، باقي ٤٨ ساعة على الإجازة، وما حجزوا شي 😅 هذي كيف خلصناها 👇 «مكالمة وحدة» الحلقة ٢ | O60: A family of 7, 48 hours to the break, nothing booked. Here's how we did it. 'One Call', episode 2. | P60: حجز رحلة عائلية, باقات عائلية, family trip planning | Q60: #مكالمة_وحدة #إجازة_الخريف #سفر_عائلي #مادا #MadaTrips | R60: Comment your request for episode 3 | S60: Same split-screen format as #1, with a checklist ticking on screen: 2 rooms connecting, child seats in the car, aisle seats together, halal-friendly restaurants. No children's faces. | T60: No children on camera (GAMR guidance). Show hands, luggage, backs. | V60: Scripted | AC60: =IF(OR(W60="",W60=0),"",(Y60+Z60+AA60+AB60)/W60)
A61: 60 | B61: 46343 | C61: Tue | D61: 21:00 | E61: TikTok | F61: Photo carousel 8 | G61: Know Before You Go | I61: Autumn break | J61: Autumn-break packing list for kids | K61: Slide 1: شنطة الأطفال للإجازة: لا تنسى رقم ٦ 👀 | L61: Kids' travel bag: don't forget #6 | M61: شنطة الأطفال: لا تنسى رقم ٦ | N61: شنطة الأطفال للإجازة 🧳 لا تنسى رقم ٦ 👀 احفظها. | O61: Kids' bag for the break. Don't forget number 6. Save it. | P61: شنطة السفر للاطفال, قائمة السفر مع الاطفال | Q61: #سفر_مع_الأطفال #إجازة_الخريف #شنطة_السفر #سفر #مادا | R61: Save | S61: Photo Mode checklist, flat-lay photos, one item per slide. #6 = a copy of the passports and the kids' birth certificates on your phone. | V61: Scripted | AC61: =IF(OR(W61="",W61=0),"",(Y61+Z61+AA61+AB61)/W61)
A62: 61 | B62: 46343 | C62: Tue | D62: 18:00 | E62: X | F62: Poll | G62: Horizons | I62: Autumn break | J62: Autumn break: where? | K62: إجازة الخريف وين؟ | N62: إجازة الخريف وين؟ 🍂 | O62: Autumn break: where? | P62: اجازة الخريف | Q62: #إجازة_الخريف | R62: Vote | S62: Poll: 🇸🇦 داخل المملكة / 🌴 خليجي / ✈️ أبعد / 🏠 البيت وموسم الرياض | V62: Scripted | AC62: =IF(OR(W62="",W62=0),"",(Y62+Z62+AA62+AB62)/W62)
A63: 62 | B63: 46343 | C63: Tue | D63: 09:30 | E63: LinkedIn | F63: Document 8 pages | G63: Events & Business | H63: Field Notes | I63: Evergreen B2B | J63: Field Notes #2: why delegates remember logistics, not keynotes | K63: Page 1: Ask a delegate about your summit a month later. They'll describe the airport. | L63: Delegates remember the airport | O63: Field Notes #2. Ask a delegate about your summit a month later. They rarely quote the keynote. They describe the airport, the car, the room and whether anyone knew their name. That's why we plan events and travel as one plan: • Arrival waves timed to the agenda • Hotel check-in waiting at registration • One WhatsApp line for every guest • A host team that sees every status live The event starts at the gate. | P63: event and travel management, delegate experience, MICE Saudi | Q63: #FieldNotes #EventProfs #MICE #Riyadh | R63: Comment / share with your events lead | S63: PDF: a guest journey map across pages (gate → car → hotel → venue → home). | V63: Scripted | AC63: =IF(OR(W63="",W63=0),"",(Y63+Z63+AA63+AB63)/W63)
A64: 63 | B64: 46344 | C64: Wed | D64: 20:30 | E64: Instagram | F64: Static 4:5 | G64: Know Before You Go | H64: Visa in 60 | I64: Evergreen visa | J64: Schengen document checklist (save-worthy) | K64: Save this before your appointment. | L64: Schengen checklist: 9 documents | M64: شنغن: ٩ أوراق لا تنساها | N64: قبل موعد الفيزا: ٩ أوراق لا تنساها 📌 احفظ المنشور وارجع له يوم الموعد. | O64: Before your visa appointment: 9 documents not to forget. Save this and come back to it on the day. | P64: اوراق فيزا شنغن, متطلبات تأشيرة شنغن, Schengen documents | Q64: #تأشيرة_شنغن #فيزا #أوروبا #سفر #مادا | R64: Save | S64: Clean checklist poster, 9 lines with tick boxes, AR main + small EN. Designed to be screenshotted. | T64: Requirements vary by embassy, so keep it general and say 'check your embassy's list'. | V64: Scripted | AC64: =IF(OR(W64="",W64=0),"",(Y64+Z64+AA64+AB64)/W64)
A65: 64 | B65: 46344 | C65: Wed | D65: 21:00 | E65: TikTok | F65: Video 45s | G65: Know Before You Go | H65: Visa in 60 | I65: Evergreen visa | J65: US visa: book your interview early | K65: On-screen + VO: مسافر أمريكا ٢٠٢٧؟ احجز موعدك الحين ⏳ | L65: US visa: book the interview now | M65: فيزا أمريكا: احجز المقابلة الحين | N65: مسافر أمريكا السنة الجاية؟ ليش لازم تحجز موعد المقابلة من الحين ⏳👇 | O65: Travelling to the US next year? Why you should book your interview now. | P65: فيزا امريكا, موعد السفارة الامريكية, US visa Saudi | Q65: #فيزا_أمريكا #أمريكا #تأشيرة #سفر #مادا | R65: Save | S65: Concierge explains: most interview waivers ended in Sep 2025, so more people need an in-person interview and wait times vary. A visa integrity fee has applied since Oct 2025 (amount on screen as announced). Book early. | T65: Verify on the US Embassy Riyadh site; describe the fee as 'announced', with the amount as published. | V65: Scripted | AC65: =IF(OR(W65="",W65=0),"",(Y65+Z65+AA65+AB65)/W65)
A66: 65 | B66: 46344 | C66: Wed | D66: 12:30 | E66: X | F66: Post | G66: One Call | I66: Lufthansa's planned return (18 Nov) | J66: Routes update (conditional) | K66: تحديث الرحلات الدولية من الرياض ✈️ | N66: تحديث: شركات طيران أوروبية تعيد جدولة رحلاتها للرياض هالشهر. إذا عندك حجز تأثر أو تبي بدائل، فريقنا يتابع التحديثات أول بأول. كلمنا. | O66: Update: European airlines are rescheduling their Riyadh services this month. If your booking was affected or you need alternatives, our team tracks updates daily. | P66: تحديثات الطيران | R66: DM | S66: Text only, factual. | T66: SENSITIVITY: only post confirmed facts from the airline itself. Skip if nothing is confirmed. | V66: Scripted | AC66: =IF(OR(W66="",W66=0),"",(Y66+Z66+AA66+AB66)/W66)
A67: 66 | B67: 46345 | C67: Thu | D67: 19:30 | E67: Instagram | F67: Carousel 7 | G67: Horizons | H67: Weekend Radar | I67: School break starts 20 Nov | J67: Weekend Radar #3: break edition | K67: Slide 1: Weekend Radar · Break edition | L67: Weekend Radar · Break edition | M67: رادار الويكند · نسخة الإجازة | N67: رادار الويكند: نسخة الإجازة 🍂 • موسم الرياض للعائلة: ونستر غاردن وبوليفارد وورلد • الكشتة: الجو صار مناسب • مسقط: اليوم الوطني العماني ٢٠ نوفمبر • لندن: Winter Wonderland يفتح اليوم | O67: Weekend Radar, break edition: Riyadh Season for families, desert camping weather is here, Oman National Day in Muscat, and London's Winter Wonderland opens today. | P67: فعاليات الاجازة, وش نسوي في الاجازة | Q67: #رادار_الويكند #إجازة_الخريف #موسم_الرياض #الرياض #مادا | R67: Save + share | S67: Weekend Radar template, autumn tint. | V67: Scripted | AC67: =IF(OR(W67="",W67=0),"",(Y67+Z67+AA67+AB67)/W67)
A68: 67 | B68: 46345 | C68: Thu | D68: 21:30 | E68: Instagram | F68: Reel 35s | G68: Horizons | H68: Europe in Winter | I68: Winter Wonderland opens 19 Nov | J68: London in winter: ETA + Winter Wonderland + 4 more | K68: Text over a London skyline: 'London in winter, done right' | L68: London in winter · done right | M68: لندن في الشتاء · صح | N68: لندن في الشتاء ❄️ Winter Wonderland فتح اليوم. ٦ أشياء نسويها لعملاءنا هناك، وأولها: الـETA قبل الحجز. | O68: London in winter. Winter Wonderland opens today. 6 things we arrange for our clients there, starting with the ETA before booking. | P68: لندن في الشتاء, Winter Wonderland London, سفر لندن | Q68: #لندن #شتاء_أوروبا #بريطانيا #سفر #مادا | R68: Save | S68: List reel: ETA, Hyde Park Winter Wonderland, a West End matinee, a halal afternoon tea, a Harrods window walk, day trip to the Cotswolds. Collab with a London-based Saudi creator if possible. | T68: Collab creator must hold a Mawthooq licence if paid. | V68: Scripted | AC68: =IF(OR(W68="",W68=0),"",(Y68+Z68+AA68+AB68)/W68)
A69: 68 | B69: 46345 | C69: Thu | D69: 20:00 | E69: TikTok | F69: Video 15s | G69: Moments & Offers | I69: Last school/work day before the break | J69: Last workday before the break | K69: On-screen: آخر يوم دوام قبل الإجازة 😮‍💨 | L69: Last day before the break | M69: آخر يوم قبل الإجازة | N69: آخر يوم دوام قبل الإجازة… الكل كذا؟ 😂 | O69: Last workday before the break. Is everyone like this? | P69: اجازة الخريف | Q69: #إجازة_الخريف #دوام #السعودية #ترند #مادا | R69: Tag a colleague | S69: Team meme on a trending sound: the clock at 13:59, then the whole team 'teleporting' out with suitcases. Relatable and real (TikTok Next 2026: 'Reali-TEA'). | T69: Keep it light. No mocking anyone (GAMR rules). | V69: Scripted | AC69: =IF(OR(W69="",W69=0),"",(Y69+Z69+AA69+AB69)/W69)
A70: 69 | B70: 46345 | C70: Thu | D70: 22:00 | E70: TikTok | F70: Photo carousel 7 | G70: Know Before You Go | I70: Break departures | J70: Airport-day checklist | K70: Slide 1: مسافر بكرة؟ سوّ هذا الليلة ✅ | L70: Flying tomorrow? Do this tonight | M70: مسافر بكرة؟ سوّ هذا الليلة | N70: مسافر بكرة؟ ٧ أشياء سوّها الليلة ✅ | O70: Flying tomorrow? 7 things to do tonight. | P70: قائمة السفر, نصائح المطار | Q70: #نصائح_سفر #إجازة_الخريف #سفر #مطار #مادا | R70: Save | S70: Checklist: online check-in, passport validity (6 months), ETA/visa copies, chargers, a pen for forms, arrival transfer confirmed, airline app notifications on. | V70: Scripted | AC70: =IF(OR(W70="",W70=0),"",(Y70+Z70+AA70+AB70)/W70)
A71: 70 | B71: 46345 | C71: Thu | D71: 13:00 | E71: X | F71: Post | G71: One Call | I71: Break | J71: Last-minute break trips | K71: ما حجزت للإجازة؟ لسه فيه وقت. | N71: ما حجزت للإجازة؟ لسه فيه وقت ⏳ عندنا خيارات داخلية وقريبة للويكند هذا. أرسل «إجازة» على الواتساب ونرد عليك خلال ساعة. | O71: Haven't booked for the break? There's still time. We have domestic and nearby options for this weekend. Send 'break' on WhatsApp and we'll reply within the hour. | P71: رحلات اللحظة الاخيرة | Q71: #إجازة_الخريف | R71: WhatsApp | S71: Text only. | T71: Ops must confirm real availability before posting. | V71: Scripted | AC71: =IF(OR(W71="",W71=0),"",(Y71+Z71+AA71+AB71)/W71)
A72: 71 | B72: 46345 | C72: Thu | D72: 09:30 | E72: LinkedIn | F72: Image + post | G72: One Call | H72: Horizon Keepers | I72: Employer brand | J72: Horizon Keepers #1: meet our visa desk | K72: She has read more embassy checklists than anyone we know. | L72: Horizon Keepers · The visa desk | O72: Horizon Keepers #1: the visa desk. She has read more embassy checklists than anyone we know. Her rule: 'Nobody should find out at the counter that a document is missing.' What the visa desk handles each week: • Schengen, UK ETA, US and Asia applications • Business visit visas for inbound delegates • Appointment hunting during peak season The people behind the plan are the plan. | P72: visa services Riyadh, business visa Saudi | Q72: #HorizonKeepers #TeamMada #Riyadh | R72: Follow | S72: A natural portrait at her desk (with consent), a quote overlay. | T72: Consent from the team member. Use her first name if she's happy to. | V72: Scripted | AC72: =IF(OR(W72="",W72=0),"",(Y72+Z72+AA72+AB72)/W72)
A73: 72 | B73: 46346 | C73: Fri | D73: 20:30 | E73: Instagram | F73: Reel 25s | G73: Moments & Offers | I73: Autumn break starts 20 Nov | J73: Break mode: ON | K73: A suitcase zips shut on the beat | L73: Break mode: ON | M73: وضع الإجازة: تشغيل | N73: وضع الإجازة: تشغيل 🍂✈️ وين أول محطة لكم؟ شاركونا بقصصكم ومنشنوا @madatrips | O73: Break mode on. Where's your first stop? Share your stories and tag @madatrips. | P73: اجازة الخريف, سفر | Q73: #إجازة_الخريف #سفر #مادا #MadaTrips #السعودية | R73: Tag us in your stories (UGC) | S73: Fast montage, beat-synced: zips, passports, car doors, boarding, a hotel door, the first view. Clients' footage only with written consent. No kids' faces. | V73: Scripted | AC73: =IF(OR(W73="",W73=0),"",(Y73+Z73+AA73+AB73)/W73)
A74: 73 | B74: 46346 | C74: Fri | D74: 21:00 | E74: TikTok | F74: Video 45s | G74: Horizons | I74: Oman National Day (20 Nov) · break | J74: Muscat in 48 hours | K74: On-screen: ساعتين طيران من الرياض… وهذا اللي ينتظرك 🇴🇲 | L74: Muscat in 48 hours | M74: مسقط في ٤٨ ساعة | N74: اليوم الوطني العماني 🇴🇲 ومسقط قريبة… هذا برنامج ٤٨ ساعة 👇 | O74: Oman National Day, and Muscat is close. Here's a 48-hour plan. | P74: مسقط سياحة, برنامج مسقط يومين, Muscat 48 hours | Q74: #مسقط #عمان #إجازة_الخريف #سفر #مادا | R74: Comment 'مسقط' for the plan | S74: Itinerary chapters: Muttrah Corniche at sunset, the Grand Mosque in the morning, a boat trip, the souq. Respectful, warm wishes to Oman. | T74: Check the National Day holiday date with Omani sources. Use respectful wording. | V74: Scripted | AC74: =IF(OR(W74="",W74=0),"",(Y74+Z74+AA74+AB74)/W74)
A75: 74 | B75: 46346 | C75: Fri | D75: 17:00 | E75: X | F75: Post | G75: One Call | I75: Break departures | J75: Safe travels + 24/7 line | K75: مسافر اليوم؟ الله يحفظك. | N75: مسافر اليوم؟ الله يحفظك وترجع بالسلامة 🤍 أي طارئ بالطريق، واتساب مادا شغال ٢٤/٧: ‎+966 56 668 2662 | O75: Travelling today? Safe travels. For anything on the way, Mada's WhatsApp is open 24/7. | Q75: #إجازة_الخريف | R75: Save the number | S75: Text only. | T75: After Friday prayer. | V75: Scripted | AC75: =IF(OR(W75="",W75=0),"",(Y75+Z75+AA75+AB75)/W75)
A76: 75 | B76: 46347 | C76: Sat | D76: 20:00 | E76: Instagram | F76: Carousel 8 | G76: Horizons | I76: Desert camping season · break weekend | J76: Kashta season: the desert camp checklist | K76: Slide 1: Kashta season is open. Here's the checklist we swear by. | L76: Kashta season · the checklist | M76: موسم الكشتة · القائمة الكاملة | N76: موسم الكشتة فتح 🔥🏜️ القائمة اللي نمشي عليها: من الحطب لين الكشاف، ونصايح الأمان اللي محد يقولها. احفظها لأول كشتة. | O76: Kashta (desert camping) season is open. Our checklist from firewood to headlamps, plus the safety tips nobody tells you. Save it for your first camp. | P76: كشتة, قائمة الكشتة, مخيمات الرياض, desert camping Riyadh | Q76: #كشتة #موسم_الكشتة #الرياض #البر #مادا | R76: Save + tag your kashta crew | S76: Photo-led slides: the setup, gear flat-lay, coffee corner, fire. Safety slide: tell someone your location, carry water and a spare tyre, check the weather, take your rubbish home. | V76: Scripted | AC76: =IF(OR(W76="",W76=0),"",(Y76+Z76+AA76+AB76)/W76)
A77: 76 | B77: 46347 | C77: Sat | D77: 21:00 | E77: TikTok | F77: Video 30s | G77: Horizons | I77: Kashta season | J77: Kashta setup ASMR | K77: Sound first: the fire crackles, the dallah pours | L77: Kashta setup · sound on | M77: تجهيز الكشتة · ارفع الصوت | N77: كشتة أول الموسم 🔥 ارفع الصوت. | O77: First kashta of the season. Sound on. | P77: كشتة, جلسة بر, مخيم | Q77: #كشتة #البر #موسم_الكشتة #السعودية #مادا | R77: Comment your kashta must-have | S77: ASMR build: carpets unrolled, the tent up, the fire lit, coffee poured, stars come out (timelapse). No VO. | V77: Scripted | AC77: =IF(OR(W77="",W77=0),"",(Y77+Z77+AA77+AB77)/W77)
A78: 77 | B78: 46347 | C78: Sat | D78: 16:30 | E78: X | F78: Poll | G78: Horizons | I78: Kashta season | J78: Kashta must-have | K78: وش أهم شي في الكشتة؟ | N78: وش أهم شي في الكشتة؟ 🔥 | O78: What matters most at a kashta? | P78: كشتة | Q78: #كشتة | R78: Vote | S78: Poll: ☕ القهوة / 🔥 الحطب / 🎶 الجلسة / 🍖 العشاء | V78: Scripted | AC78: =IF(OR(W78="",W78=0),"",(Y78+Z78+AA78+AB78)/W78)
A79: 78 | B79: 46348 | C79: Sun | D79: 20:30 | E79: Instagram | F79: Reel 40s | G79: One Call | H79: Concierge Confessions | I79: Evergreen | J79: Concierge Confessions #2: the 2am rebooking | K79: On-screen: 'The flight's cancelled.' 'OK. Give me 20 minutes.' | L79: 02:00 · 20 minutes · new route | M79: ٢ الفجر · ٢٠ دقيقة · مسار جديد | N79: رحلة ألغيت الساعة ٢ الفجر… و٢٠ دقيقة بعدها كان فيه مسار جديد، فندق، وسيارة تنتظر. «من دفتر الكونسيرج» الحلقة ٢ | O79: A flight cancelled at 2 a.m., and 20 minutes later a new route, a hotel and a car waiting. 'Concierge Confessions', episode 2. | P79: الغاء رحلة وش اسوي, travel concierge | Q79: #من_دفتر_الكونسيرج #مادا #سفر #MadaTrips #قصص_سفر | R79: Save + follow | S79: Same storytime format. Calm, reassuring tone. Focus on the fix, not the problem. | T79: SENSITIVITY: no reference to the October attacks. Keep the story generic (weather, technical). | V79: Scripted | AC79: =IF(OR(W79="",W79=0),"",(Y79+Z79+AA79+AB79)/W79)
A80: 79 | B80: 46348 | C80: Sun | D80: 21:00 | E80: TikTok | F80: Video 50s | G80: Horizons | I80: Break week · Riyadh Season | J80: Riyadh Season with family: the 1-day plan | K80: On-screen: يوم كامل بموسم الرياض مع العائلة… بدون تعب 👨‍👩‍👧 | L80: Riyadh Season with family: 1-day plan | M80: موسم الرياض مع العائلة: خطة يوم | N80: يوم كامل بموسم الرياض مع العائلة بدون تعب 👨‍👩‍👧 احفظ الخطة. | O80: A full day at Riyadh Season with the family, without the exhaustion. Save the plan. | P80: موسم الرياض للعائلات, وش يناسب الاطفال في موسم الرياض | Q80: #موسم_الرياض #عائلة #إجازة_الخريف #الرياض #مادا | R80: Save | S80: Timeline video: 4pm Wonder Garden → 6pm early dinner → 7:30pm Boulevard World pavilions → 10pm home. Tips on strollers, breaks, meeting points. | T80: No children's faces. | V80: Scripted | AC80: =IF(OR(W80="",W80=0),"",(Y80+Z80+AA80+AB80)/W80)
A81: 80 | B81: 46348 | C81: Sun | D81: 13:00 | E81: X | F81: Thread 5 | G81: Horizons | I81: Break week | J81: Riyadh Season with family thread | K81: موسم الرياض مع العائلة: خطة يوم كامل 🧵 | N81: ١/ موسم الرياض مع العائلة: خطة يوم كامل بدون تعب 🧵 ٢/ ٤ العصر: ونستر غاردن قبل الزحمة ٣/ ٦ المغرب: عشاء بدري ٤/ ٧:٣٠: أجنحة بوليفارد وورلد ٥/ ١٠ بالليل: الرجعة قبل ذروة الطلعة. وتبي تذاكر أو سيارة؟ كلمنا. | O81: 1/ Riyadh Season with family: a full-day plan. 2/ 4pm Wonder Garden before the crowds. 3/ 6pm early dinner. 4/ 7:30 Boulevard World pavilions. 5/ 10pm head home before the rush. Need tickets or a car? Talk to us. | P81: موسم الرياض للعائلات | Q81: #موسم_الرياض | R81: DM | S81: Text thread. | V81: Scripted | AC81: =IF(OR(W81="",W81=0),"",(Y81+Z81+AA81+AB81)/W81)
A82: 81 | B82: 46348 | C82: Sun | D82: 09:30 | E82: LinkedIn | F82: Document 7 pages | G82: Events & Business | H82: Field Notes | I82: Q4 budgeting season | J82: Field Notes #3: 5 travel-policy clauses that save money in 2027 | K82: Page 1: Most travel policies were written for 2019. | L82: 5 travel-policy clauses for 2027 | O82: Field Notes #3. Most corporate travel policies were written for a world that no longer exists. 5 clauses we recommend for 2027: 1. Book by default 21+ days ahead, with exceptions approved in one tap 2. Flexible fares for any trip with a fixed meeting 3. Preferred hotels near the work, not near the airport 4. A single 24/7 line for disruptions 5. Monthly reporting by project and cost centre Which one would your finance team push back on? | P82: corporate travel policy, travel management company Saudi Arabia | Q82: #FieldNotes #CorporateTravel #Procurement #Finance | R82: Comment | S82: PDF document, a policy-document look (numbered clauses, margins). | V82: Scripted | AC82: =IF(OR(W82="",W82=0),"",(Y82+Z82+AA82+AB82)/W82)
A83: 82 | B83: 46349 | C83: Mon | D83: 20:30 | E83: Instagram | F83: Carousel 8 | G83: Horizons | I83: Trend: destination dupes | J83: Destination dupes: love X? try Y | K83: Slide 1: Love Switzerland? You might love this more (and it's closer). | L83: Destination dupes | M83: بدائل الوجهات | N83: تحب سويسرا؟ جرب جورجيا 🏔️ تحب المالديف؟ جرب البحر الأحمر 🌊 تحب الأندلس؟ جرب الدرعية 🏛️ بدائل أقرب، وأحياناً أحلى. وش البديل اللي تقترحه؟ | O83: Love Switzerland? Try Georgia. Love the Maldives? Try the Red Sea. Love Andalusia? Try Diriyah. Closer alternatives, sometimes better. What dupe would you suggest? | P83: بدائل سويسرا, البحر الاحمر بديل المالديف, destination dupes | Q83: #سفر #البحر_الأحمر #جورجيا #الدرعية #مادا | R83: Comment your dupe | S83: Side-by-side split slides 'Love → Try'. Real photos. The 'dupe' structure is a strong save/share trigger. | V83: Scripted | AC83: =IF(OR(W83="",W83=0),"",(Y83+Z83+AA83+AB83)/W83)
A84: 83 | B84: 46349 | C84: Mon | D84: 21:00 | E84: TikTok | F84: Video 40s | G84: Horizons | I84: Trend: dupes | J84: Dupes: Switzerland? Try this | K84: On-screen: سويسرا غالية؟ 👀 جرب هذي | L84: Switzerland? Try this. | M84: سويسرا؟ جرب هذي | N84: بدائل الوجهات المشهورة… أقرب وأوفر 👀 أي واحد يستاهل؟ | O84: Alternatives to famous destinations, closer and better value. Which one is worth it? | P84: بديل سويسرا, جورجيا في الشتاء, Gudauri | Q84: #جورجيا #سفر #بدائل_سياحية #شتاء #مادا | R84: Comment 'worth it?' | S84: Green-screen 'this or that' with Gudauri snow (Georgia ski season opens around December), Red Sea, Diriyah. | V84: Scripted | AC84: =IF(OR(W84="",W84=0),"",(Y84+Z84+AA84+AB84)/W84)
A85: 84 | B85: 46349 | C85: Mon | D85: 12:30 | E85: X | F85: Thread 4 | G85: Know Before You Go | I85: China visa-free window ends 31 Dec | J85: Visa-free reminders: China & Russia | K85: دولتين تقدر تسافر لها بدون فيزا هالسنة 🧵 | N85: ١/ دولتين تقدر تسافر لها بجوازك السعودي بدون فيزا هالسنة 🧵 ٢/ الصين: دخول بدون تأشيرة ممدد لين ٣١ ديسمبر ٢٠٢٦ ٣/ روسيا: بدون تأشيرة من مايو ٢٠٢٦، لين ٩٠ يوم بالسنة ٤/ تحقق من الشروط قبل الحجز، وتبي برنامج؟ كلمنا. | O85: 1/ Two countries you can visit visa-free on a Saudi passport this year. 2/ China: visa-free entry extended to 31 Dec 2026. 3/ Russia: visa-free since May 2026, up to 90 days a year. 4/ Check the conditions before booking. | P85: بدون فيزا للسعوديين, الصين بدون تأشيرة | Q85: #بدون_فيزا | R85: Bookmark | S85: Text thread. | T85: Verify both rules with the official embassy pages the week of posting. | V85: Scripted | AC85: =IF(OR(W85="",W85=0),"",(Y85+Z85+AA85+AB85)/W85)
A86: 85 | B86: 46350 | C86: Tue | D86: 20:30 | E86: Instagram | F86: Reel 35s | G86: Events & Business | H86: Behind the Curtain | I86: Evergreen events | J86: Behind the Curtain #2: a gala run to the second | K86: A show caller's voice: 'Standby cue 14… go.' | L86: Cue 14 · go | M86: الإشارة ١٤ · انطلق | N86: «استعداد… الإشارة ١٤… انطلق» كل حفل ناجح وراه شخص يمشي الفعالية بالثانية. «خلف الستارة» الحلقة ٢. | O86: 'Standby… cue 14… go.' Behind every great gala is someone running it to the second. 'Behind the Curtain', episode 2. | P86: تنظيم حفلات الرياض, تنظيم حفل جوائز, gala event Riyadh | Q86: #خلف_الستارة #تنظيم_فعاليات #حفلات #مادا #MadaEvents | R86: DM 'EVENT' | S86: Show-caller POV from the control desk: headset audio, a run-of-show sheet, cues hitting on stage. Real event footage. | T86: Needs our own event footage. | V86: Scripted | AC86: =IF(OR(W86="",W86=0),"",(Y86+Z86+AA86+AB86)/W86)
A87: 86 | B87: 46350 | C87: Tue | D87: 21:00 | E87: TikTok | F87: Video 45s | G87: One Call | I87: Trend: day in the life / Reali-TEA | J87: Day in the life of a Mada concierge | K87: On-screen: يوم كامل مع كونسيرج سفر بالرياض ☕📞 | L87: A day with a Riyadh travel concierge | M87: يوم مع كونسيرج سفر بالرياض | N87: يوم كامل مع كونسيرج سفر بالرياض ☕📞 وش تتوقع أغرب طلب جانا؟ | O87: A full day with a travel concierge in Riyadh. Guess the strangest request we've had? | P87: يومي في العمل, وظيفة كونسيرج, day in the life travel agent | Q87: #يوم_في_حياتي #مادا #سفر #الرياض #DayInTheLife | R87: Guess in comments | S87: Vlog style, 8 time-stamped beats from 08:00 coffee to 23:00 'one more call'. Natural, lightly funny, real. | V87: Scripted | AC87: =IF(OR(W87="",W87=0),"",(Y87+Z87+AA87+AB87)/W87)
A88: 87 | B88: 46350 | C88: Tue | D88: 13:00 | E88: X | F88: Post | G88: Moments & Offers | I88: White Friday 27 Nov | J88: White Friday teaser | K88: الجمعة البيضاء جاية… 👀 | N88: الجمعة البيضاء جاية ٢٧ نوفمبر 👀 ردّ بـ«🤍» ونرسل لك العرض قبل الكل. | O88: White Friday is coming on 27 November. Reply with 🤍 and we'll send you the offer first. | P88: الجمعة البيضاء عروض سفر | Q88: #الجمعة_البيضاء | R88: Reply 🤍 | S88: Text only. | T88: Build an early-access list from the replies (DM each one on the day). | V88: Scripted | AC88: =IF(OR(W88="",W88=0),"",(Y88+Z88+AA88+AB88)/W88)
A89: 88 | B89: 46350 | C89: Tue | D89: 09:30 | E89: LinkedIn | F89: Image + post | G89: Events & Business | I89: Evergreen B2B | J89: Specialist supply: the expert you couldn't find | K89: The project needed one person. There were four in the region. | L89: The expert you couldn't find. Found. | O89: A client needed one specialist for a commissioning phase. There were maybe four people in the region with that exact certification, and all were booked. We found the fifth, cleared the visa and had them on site in 11 days. Specialist supply is about the network and the paperwork. One without the other doesn't work. If your 2027 projects have roles you're already worried about, talk to us early. | P89: specialist recruitment Saudi Arabia, technical specialists KSA | Q89: #SpecialistSupply #Engineering #SaudiArabia #Projects | R89: Message us | S89: One image: a minimalist search graphic (5 dots, one lit). | T89: Use a real case with numbers confirmed by ops. | V89: Scripted | AC89: =IF(OR(W89="",W89=0),"",(Y89+Z89+AA89+AB89)/W89)
A90: 89 | B90: 46351 | C90: Wed | D90: 20:30 | E90: Instagram | F90: Static 4:5 | G90: Moments & Offers | I90: White Friday countdown | J90: White Friday: 2 days | K90: 2 days. | L90: White Friday · 2 days | M90: الجمعة البيضاء · باقي يومين | N90: باقي يومين 🤍 فعّل التنبيهات عشان ما يفوتك. | O90: Two days. Turn on notifications so you don't miss it. | P90: الجمعة البيضاء | Q90: #الجمعة_البيضاء #عروض_سفر #مادا #MadaTrips #الرياض | R90: Turn on notifications | S90: Minimal: a big '2' in white on green, a soft sand texture. Story version with a countdown sticker (people can tap 'remind me'). | V90: Scripted | AC90: =IF(OR(W90="",W90=0),"",(Y90+Z90+AA90+AB90)/W90)
A91: 90 | B91: 46351 | C91: Wed | D91: 21:00 | E91: TikTok | F91: Video 40s | G91: Know Before You Go | I91: Evergreen | J91: Travel myths: real or fake? | K91: On-screen: الحجز يوم الثلاثاء أرخص؟ 🤔 حقيقة ولا خرافة | L91: Travel myths: real or fake? | M91: خرافات السفر: حقيقة ولا لا؟ | N91: ٥ خرافات عن حجز السفر… كم وحدة كنت مصدقها؟ 😅 | O91: 5 myths about booking travel. How many did you believe? | P91: نصائح حجز طيران, ارخص وقت للحجز | Q91: #نصائح_سفر #سفر #حجز_طيران #السعودية #مادا | R91: Comment your score /5 | S91: Green-screen myth-busting with a ✅/❌ stamp: Tuesday booking, incognito mode, 'last minute is always cheaper', 'refundable is never worth it', 'one-way is always pricier'. Give the honest nuance. | V91: Scripted | AC91: =IF(OR(W91="",W91=0),"",(Y91+Z91+AA91+AB91)/W91)
A92: 91 | B92: 46351 | C92: Wed | D92: 13:00 | E92: X | F92: Thread 5 | G92: Know Before You Go | I92: Evergreen | J92: Booking myths thread | K92: ٥ خرافات عن حجز الطيران 🧵 | N92: ١/ ٥ خرافات عن حجز الطيران 🧵 ٢/ «الثلاثاء أرخص»: الأسعار تتغير حسب الطلب، مو حسب اليوم. ٣/ «التصفح الخفي يرخص السعر»: ما فيه دليل قوي. ٤/ «آخر لحظة دايم أرخص»: بمواسم الإجازات العكس غالباً. ٥/ «المرن ما يستاهل»: إذا عندك اجتماع ثابت، يستاهل. | O92: 1/ 5 myths about booking flights. 2/ 'Tuesday is cheaper': prices move with demand, not the day. 3/ 'Incognito lowers prices': no solid evidence. 4/ 'Last minute is always cheaper': in holiday peaks it's usually the opposite. 5/ 'Flexible isn't worth it': with a fixed meeting, it is. | P92: نصائح حجز طيران | Q92: #نصائح_سفر | R92: Bookmark | S92: Text thread. | V92: Scripted | AC92: =IF(OR(W92="",W92=0),"",(Y92+Z92+AA92+AB92)/W92)
A93: 92 | B93: 46352 | C93: Thu | D93: 19:30 | E93: Instagram | F93: Carousel 7 | G93: Horizons | H93: Weekend Radar | I93: F1 Qatar 27-29 Nov · White Friday | J93: Weekend Radar #4 | K93: Slide 1: Weekend Radar · 26-28 Nov | L93: Weekend Radar · 26-28 Nov | M93: رادار الويكند · ٢٦–٢٨ نوفمبر | N93: رادار الويكند 📡 • الجمعة: الجمعة البيضاء 🤍 • الدوحة: جائزة قطر للفورمولا ١ (٢٧–٢٩) • ستراسبورغ: سوق الشتاء يفتح اليوم • آخر ويكند بالإجازة: موسم الرياض والكشتة | O93: Weekend Radar: White Friday, the F1 Qatar Grand Prix (27-29), Strasbourg's winter market opens today, and the last weekend of the break. | P93: فعاليات الويكند, F1 Qatar 2026 | Q93: #رادار_الويكند #موسم_الرياض #فورمولا1 #الرياض #مادا | R93: Save + share | S93: Weekend Radar template. | T93: Check F1 Qatar is going ahead (regional uncertainty reported). | V93: Scripted | AC93: =IF(OR(W93="",W93=0),"",(Y93+Z93+AA93+AB93)/W93)
A94: 93 | B94: 46352 | C94: Thu | D94: 21:30 | E94: Instagram | F94: Reel 20s | G94: Moments & Offers | I94: White Friday eve | J94: White Friday tomorrow: how it works | K94: On-screen: Tomorrow. Here's how it works. | L94: White Friday · tomorrow | M94: الجمعة البيضاء · بكرة | N94: بكرة الجمعة البيضاء 🤍 كيف تستفيد: ١ فعّل التنبيه ٢ جهز وجهتك وتواريخك ٣ أرسل «🤍» على الواتساب أول ما يبدأ. | O94: White Friday is tomorrow. Turn on notifications, have your destination and dates ready, and send 🤍 on WhatsApp when it starts. | P94: عروض الجمعة البيضاء سفر | Q94: #الجمعة_البيضاء #عروض_سفر #مادا #سفر #الرياض | R94: Turn on notifications | S94: Three-step explainer with a phone-screen mockup. A simple loop. | V94: Scripted | AC94: =IF(OR(W94="",W94=0),"",(Y94+Z94+AA94+AB94)/W94)
A95: 94 | B95: 46352 | C95: Thu | D95: 20:00 | E95: TikTok | F95: Video 30s | G95: Horizons | I95: F1 Qatar GP 27-29 Nov | J95: F1 Qatar weekend: Riyadh to Doha | K95: On-screen: أقل من ساعتين من الرياض… وأنت بالفورمولا ١ 🏎️ | L95: Under 2 hours to F1 | M95: أقل من ساعتين… وأنت بالفورمولا ١ | N95: جائزة قطر الكبرى للفورمولا ١ هالويكند 🏎️ أقل من ساعتين طيران من الرياض. تلحق؟ | O95: The F1 Qatar Grand Prix is this weekend, under 2 hours' flight from Riyadh. Can you make it? | P95: فورمولا ١ قطر, F1 Qatar 2026 tickets, لوسيل | Q95: #فورمولا1 #قطر #F1 #سفر #مادا | R95: Comment 'ألحق' | S95: Countdown energy, a flight-path animation RUH → DOH, a quick package outline (flight, hotel, grandstand, transfers). No F1 broadcast footage. | T95: Confirm the race status and ticket availability before posting. No F1 logos. | V95: Scripted | AC95: =IF(OR(W95="",W95=0),"",(Y95+Z95+AA95+AB95)/W95)
A96: 95 | B96: 46352 | C96: Thu | D96: 22:00 | E96: TikTok | F96: Video 20s | G96: Moments & Offers | I96: White Friday eve | J96: White Friday preview | K96: On-screen: عرض بكرة… تلميح 👀 | L96: A hint for tomorrow | M96: تلميح لعرض بكرة | N96: تلميح لعرض بكرة 👀 خمّن الوجهة. | O96: A hint for tomorrow's offer. Guess the destination. | P96: عروض الجمعة البيضاء | Q96: #الجمعة_البيضاء #عروض_سفر #سفر #السعودية #مادا | R96: Guess in comments | S96: Blurred destination reveal with sound cues (waves? snow?). The comment guessing game boosts reach. | V96: Scripted | AC96: =IF(OR(W96="",W96=0),"",(Y96+Z96+AA96+AB96)/W96)
A97: 96 | B97: 46352 | C97: Thu | D97: 13:00 | E97: X | F97: Post | G97: Moments & Offers | I97: White Friday eve | J97: White Friday rules | K97: بكرة الجمعة البيضاء 🤍 القوانين بسيطة: | N97: بكرة الجمعة البيضاء 🤍 القوانين بسيطة: • العرض يبدأ ٨ الصباح • محدود بعدد حجوزات • بدون أكواد، بس أرسل «🤍» على الواتساب اللي ردوا بـ🤍 أمس، يوصلكم قبل الكل. | O97: White Friday tomorrow. The offer starts at 8 a.m., limited bookings, no codes: just send 🤍 on WhatsApp. Those who replied yesterday get it first. | P97: الجمعة البيضاء | Q97: #الجمعة_البيضاء | R97: Turn on notifications | S97: Text only. | T97: Final terms from management. | V97: Scripted | AC97: =IF(OR(W97="",W97=0),"",(Y97+Z97+AA97+AB97)/W97)
A98: 97 | B98: 46352 | C98: Thu | D98: 09:30 | E98: LinkedIn | F98: Post | G98: Events & Business | I98: B2B White Friday equivalent | J98: Plan Q1 2027 events at 2026 rates | K98: Your Q1 2027 events will be planned in December. Here's an offer for doing it now. | L98: Q1 2027 events · 2026 rates | O98: Q1 2027 is going to be busy: the Saudi Cup in early February, then Ramadan from around 8 February. If you're planning Q1 delegations, offsites or launches, confirm by 10 December and we'll hold 2026 service rates across travel, hotels and event production. One brief, one plan, one invoice. | P98: event planning Q1 2027 Riyadh, corporate offsite Saudi Arabia | Q98: #EventPlanning #Riyadh #CorporateEvents #MICE | R98: DM / email | S98: Text post + a simple Q1 timeline image (Saudi Cup 5-6 Feb, Ramadan ~8 Feb). | T98: OFFER needs management approval. | V98: Scripted | AC98: =IF(OR(W98="",W98=0),"",(Y98+Z98+AA98+AB98)/W98)
A99: 98 | B99: 46353 | C99: Fri | D99: 08:00 | E99: Instagram | F99: Carousel 5 | G99: Moments & Offers | I99: White Friday 27 Nov | J99: White Friday: the offer | K99: Slide 1: White Friday is on. | L99: White Friday · Today only | M99: الجمعة البيضاء · اليوم فقط | N99: الجمعة البيضاء بدأت 🤍 [تفاصيل العرض] اليوم فقط، والعدد محدود. أرسل «🤍» على الواتساب ‎+966 56 668 2662 | O99: White Friday is on. [Offer details]. Today only, limited numbers. Send 🤍 on WhatsApp. | P99: عروض الجمعة البيضاء, عروض سفر, باقات سياحية | Q99: #الجمعة_البيضاء #عروض_سفر #مادا #MadaTrips #باقات_سياحية | R99: WhatsApp 🤍 | S99: Hero design: white-on-green, gold accent. Slide 1 offer, slides 2-4 three destination options with what's included (no strike-through 'was/now' unless legally verified), slide 5 terms + CTA. | T99: MANAGEMENT: final offer, terms and real prices. Follow Saudi consumer-protection rules on discount claims (Ministry of Commerce). | V99: Scripted | AC99: =IF(OR(W99="",W99=0),"",(Y99+Z99+AA99+AB99)/W99)
A100: 99 | B100: 46353 | C100: Fri | D100: 21:00 | E100: Instagram | F100: Reel 15s | G100: Moments & Offers | I100: White Friday | J100: White Friday: final hours | K100: On-screen: Final hours 🤍 | L100: Final hours | M100: الساعات الأخيرة | N100: الساعات الأخيرة 🤍 أرسل «🤍» على الواتساب قبل منتصف الليل. | O100: Final hours. Send 🤍 on WhatsApp before midnight. | P100: عروض الجمعة البيضاء | Q100: #الجمعة_البيضاء #عروض_سفر #مادا #سفر #الرياض | R100: WhatsApp | S100: A clock-hand loop over destination shots. Short and urgent, still calm. | V100: Scripted | AC100: =IF(OR(W100="",W100=0),"",(Y100+Z100+AA100+AB100)/W100)
...

Sheet Month view
A1: November 2026 at a glance
A2: Saudi week: Sunday-Thursday work, Friday-Saturday weekend. Bold = moment of the day.
A4: Sunday | B4: Monday | C4: Tuesday | D4: Wednesday | E4: Thursday | F4: Friday | G4: Saturday
A5: 1 Nov — Brand launch IN · Reel · Launch film: Every horizon, within reach TI · Video · POV: you said it once and it just happened X · Post · Launch post LI · Image · Mada Trips opens its doors | B5: 2 Nov — Launch week IN · Carousel · 9 services. 1 call. TI · Video · Schengen 5-year visa for Saudis X · Thread · Schengen 5-year visa thread | C5: 3 Nov — Launch week IN · Static · A note from our founder TI · Video · 5 things nobody tells you about Riyadh Season X · Post · Disruption help line LI · Document · Hosting international delegates in Riyadh: the checklist | D5: 4 Nov — AlUla Skies Festival 6-15 Nov IN · Reel · One Call #1: three rooms for AlUla Skies TI · Video · AlUla Skies Festival: what to do X · Poll · AlUla: which one? | E5: 5 Nov — Riyadh Season, AlUla Skies, WWE Crown Jewel (7 Nov) IN · Carousel · Weekend Radar #1 IN · Reel · Pack with me: AlUla in November TI · Video · Riyadh Season zones in 60 seconds TI · Photo · Rate my itinerary: 3 days in AlUla X · Thread · Weekend Radar on X | F5: 6 Nov — AlUla Skies opening day IN · Reel · 06:00 in AlUla (balloon ASMR) TI · Video · POV: 6am in AlUla X · Post · AlUla Skies opens today | G5: 7 Nov — WWE Crown Jewel (7 Nov) IN · Carousel · Big night in Riyadh: the stress-free plan TI · Video · Riyadh tonight X · Post · Crown Jewel night tip
A6: 8 Nov — Winter in London (Winter Wonderland from 19 Nov) IN · Reel · Concierge Confessions #1: the 3am call TI · Video · UK ETA for Saudis X · Thread · UK ETA thread LI · Document · Field Notes #1: a 200-person delegation, the 12-week timeline | B6: 9 Nov — New moon 9 Nov · AlUla Skies IN · Carousel · The darkest nights of the year are this week TI · Video · Why tonight is the darkest night X · Post · Stargazing nudge | C6: 10 Nov — AlUla Skies IN · Reel · Behind the Curtain #1: an event build in 30 seconds TI · Photo · What a weekend in AlUla actually costs X · Post · 11.11 teaser LI · Post · Hiring skilled crews in KSA: what actually takes time | D6: 11 Nov — 11.11 Singles Day / ~1 Jumada II IN · Static · 11.11: 11 bookings, 11 upgrades TI · Video · 11.11: what an 'upgrade' means X · Post · 11.11 live | E6: 12 Nov — Vienna Schönbrunn market from 6 Nov · Rathausplatz ~13 Nov IN · Carousel · Weekend Radar #2 IN · Reel · Vienna in winter: 3 days TI · Video · Europe this winter: 5 cities ranked for families TI · Video · Reply: how long does a Schengen visa take? X · Thread · Europe's winter markets 2026: opening dates LI · Post · Why we answer at 3 a.m. | F6: 13 Nov — World Kindness Day (13 Nov) IN · Reel · Small things we do that nobody asks for TI · Video · Things we do without being asked X · Post · World Kindness Day question | G6: 14 Nov — School autumn break 20-28 Nov IN · Carousel · Autumn break: 6 short trips from Riyadh TI · Video · Autumn break in 6 days: 5 nearby escapes X · Post · Autumn break countdown
A7: 15 Nov — Leonids peak 15 Nov · AlUla Skies closes IN · Reel · Tonight: the Leonids TI · Video · Where to see the meteors near Riyadh X · Post · Leonids alert LI · Document · Cityscape Global week: visitor logistics | B7: 16 Nov — International Day for Tolerance (16 Nov) · Cityscape visitors IN · Carousel · Hosting guests from abroad: a Saudi hospitality guide TI · Video · Saudi coffee etiquette in 30 seconds X · Thread · Cityscape Global: visitor tips | C7: 17 Nov — Autumn break IN · Reel · One Call #2: a family of 7, 48 hours to plan TI · Photo · Autumn-break packing list for kids X · Poll · Autumn break: where? LI · Document · Field Notes #2: why delegates remember logistics, not keynotes | D7: 18 Nov — Lufthansa's planned return (18 Nov) IN · Static · Schengen document checklist (save-worthy) TI · Video · US visa: book your interview early X · Post · Routes update (conditional) | E7: 19 Nov — School break starts 20 Nov IN · Carousel · Weekend Radar #3: break edition IN · Reel · London in winter: ETA + Winter Wonderland + 4 more TI · Video · Last workday before the break TI · Photo · Airport-day checklist X · Post · Last-minute break trips LI · Image · Horizon Keepers #1: meet our visa desk | F7: 20 Nov — Autumn break starts 20 Nov IN · Reel · Break mode: ON TI · Video · Muscat in 48 hours X · Post · Safe travels + 24/7 line | G7: 21 Nov — Desert camping season · break weekend IN · Carousel · Kashta season: the desert camp checklist TI · Video · Kashta setup ASMR X · Poll · Kashta must-have
A8: 22 Nov — Break week · Riyadh Season IN · Reel · Concierge Confessions #2: the 2am rebooking TI · Video · Riyadh Season with family: the 1-day plan X · Thread · Riyadh Season with family thread LI · Document · Field Notes #3: 5 travel-policy clauses that save money in 2027 | B8: 23 Nov — Trend: destination dupes IN · Carousel · Destination dupes: love X? try Y TI · Video · Dupes: Switzerland? Try this X · Thread · Visa-free reminders: China & Russia | C8: 24 Nov — Trend: day in the life / Reali-TEA IN · Reel · Behind the Curtain #2: a gala run to the second TI · Video · Day in the life of a Mada concierge X · Post · White Friday teaser LI · Image · Specialist supply: the expert you couldn't find | D8: 25 Nov — White Friday countdown IN · Static · White Friday: 2 days TI · Video · Travel myths: real or fake? X · Thread · Booking myths thread | E8: 26 Nov — F1 Qatar 27-29 Nov · White Friday IN · Carousel · Weekend Radar #4 IN · Reel · White Friday tomorrow: how it works TI · Video · F1 Qatar weekend: Riyadh to Doha TI · Video · White Friday preview X · Post · White Friday rules LI · Post · Plan Q1 2027 events at 2026 rates | F8: 27 Nov — White Friday 27 Nov IN · Carousel · White Friday: the offer IN · Reel · White Friday: final hours TI · LIVE · White Friday LIVE: Ask the concierge X · Post · White Friday is live | G8: 28 Nov — End of autumn break IN · Reel · Break recap: where our clients went TI · Video · Last day of the break mood X · Post · How was your trip?
A9: 29 Nov — 1 Rajab 1448 ≈ 10 Dec 2026 IN · Carousel · Rajab starts 10 Dec: plan your Umrah calmly TI · Video · Umrah, step by step #1: before you go X · Post · Ramadan Umrah: book early LI · Post · Our first month, in numbers | B9: 30 Nov — December preview IN · Reel · December on the horizon TI · Video · December in Saudi & the Gulf: 5 dates X · Post · Cyber Monday + December
A11: Shaded gold = school autumn break (20-28 Nov). IG = Instagram · TI = TikTok · X = X · LI = LinkedIn.

Sheet Platform playbook
A1: Platform playbook
A2: Each platform has its own job. Same idea, native execution, never a cross-post.
A4: Platform | B4: Role | C4: Cadence | D4: Language | E4: Best times (AST) | F4: Formats that work | G4: Rules
A5: Instagram | B5: Brand home and conversion. Discovery through Reels, saves and shares through carousels. | C5: 1-2 feed posts a day (35 this month: 18 Reels, 13 carousels, 4 statics) + Stories every day | D5: Arabic first, with English underneath (bilingual captions). On-screen text in Arabic, with English where the post is for visitors. | E5: Weekdays 20:30. Thursday 19:30 (Weekend Radar) + 21:30. Weekend evenings 20:00-21:00. Avoid the Friday prayer window (11:30-13:30). | F5: • Reels 20-45s (up to 3 min allowed): discovery. Instagram ranks on watch time, likes per reach and sends per reach (Mosseri, Jan 2025) • Carousels 6-10 slides, 4:5 or 3:4: the highest engagement per reach (6.9% vs Reels 3.3%, Buffer 2026). Use for itineraries, checklists, radars • Statics: offers, quotes and save-worthy checklists only • Stories daily: polls, question box, BTS, countdowns. Stories don't need to be polished • Trial Reels: test 2 hooks for the same idea on non-followers before posting to the grid | G5: • Max 5 hashtags (cap announced Dec 2025). Use 2-3 topic tags + #مادا • Original footage only. Since 30 Apr 2026 Instagram stops recommending accounts that mostly repost. Work with creators through Collab posts • Grid previews at 3:4, so keep key text in the centre of 4:5 images • Safe zone on Reels: no text in the top ~250px or bottom ~340px • Put the keyword in the first caption line and in the on-screen text
A6: TikTok | B6: Reach and search. The biggest platform in KSA (38.6M ad reach, 154% of adults, highest TikTok penetration in the world). | C6: 1-2 videos a day (34 this month), plus video replies to comments | D6: Saudi Arabic (white Najdi/Khaleeji) in voice and on screen. One English-led video a week for expats and visitors. | E6: 21:00 main slot, 22:00 second slot on Thursdays. 20:00-23:00 is the modelled KSA peak. | F6: • Talking-head explainers 40-60s (Visa in 60). Videos over 60s get 43% more reach (Buffer, 1.1M videos) • Relatable trend videos 15-20s (Reali-TEA, TikTok Next 2026) • Photo Mode carousels for itineraries, costs and checklists. On-slide text is searchable • Reply-to-comment videos: free content ideas and community proof • LIVE once the account has 1,000 followers | G6: • Say the keyword in the first 3 seconds, show it on screen, write it in the caption's first line and use it in 1-2 hashtags. TikTok search reads all four • Max 5 hashtags (cap since mid-2025) • Hook in the first 2 seconds: text overlay + movement. Target a 3-second hold of 35%+ • Burn in captions. Most viewers watch muted • Reply to comments for the first hour after posting
A7: X (Twitter) | B7: News, visa updates, live moments and fast customer care. Where Saudi conversations happen in real time. | C7: 1 planned post a day (30 this month) + 1-3 reactive posts and replies a day | D7: Arabic. Short, direct, dialect-friendly. | E7: 12:00-13:00 for useful posts and threads, 18:00-21:30 for live moments. | F7: • Text posts and threads: the highest median engagement on X (3.56%, Buffer 2026) • Polls for light engagement • Native images (the Weekend Radar cover). Avoid bare links (link posts have the lowest engagement: 2.25%) | G7: • Space posts at least 3 hours apart. X's ranker (open-sourced Jan 2026) downranks the 3rd-5th post from the same author in a short window • Get X Premium (Basic) for the company account. Verified accounts have a higher score ceiling • Reply to every reply in the first hour. Replies feed the ranking • Never argue in public. Move complaints to DM within 15 minutes
A8: LinkedIn | B8: B2B credibility: corporates, delegations, events, manpower, specialists, IT. Lighter touch. | C8: 3 posts a week (12 this month): Sunday, Tuesday, Thursday | D8: English (Arabic for national moments). | E8: 09:30 on Saudi workdays (Sunday-Thursday). | F8: • Document (PDF) carousels: the top LinkedIn format in 2026 (Buffer and Socialinsider) • Founder-voice text posts with one real photo • Team spotlights (Horizon Keepers) | G8: • Teach something in every post (Field Notes). LinkedIn's 2026 ranking cuts low-substance posts and engagement bait • The founder posts and the company page reshares. Personal profiles reach further • Ask the team to comment with substance in the first hour, never just 'congrats' • Put links in the post only when needed. Reach drops with external links (vendor estimates of 25-60%)

Sheet Pillars & series
A1: Content pillars and recurring series
A4: Code | B4: Pillar | C4: Target share | D4: What goes here | E4: Series
A5: ONE | B5: One Call | C5: 20% | D5: The concierge in action: real requests, the 3am rescue, small kind gestures, a day in the life. The human face no competitor shows. | E5: One Call · Concierge Confessions · Horizon Keepers
A6: KNOW | B6: Know Before You Go | C6: 20% | D6: Search-led explainers: visas, checklists, myths, Umrah steps. Built to be saved and found in search. | E6: Visa in 60 · Umrah, Step by Step
A7: HOR | B7: Horizons | C7: 35% | D7: Where to go and how: Riyadh Season, AlUla, short-haul breaks, Europe in winter, dupes, itineraries and real costs. | E7: Weekend Radar · Europe in Winter
A8: BIZ | B8: Events & Business | C8: 10% | D8: Mada Events craft and B2B: delegations, MICE, manpower, specialists, IT. Mostly LinkedIn, plus one events Reel every two weeks. | E8: Behind the Curtain · Field Notes
A9: MOM | B9: Moments & Offers | C9: 15% | D9: The launch, 11.11, World Kindness Day, the break, White Friday, December. Culture and conversion. | E9: Launch · 11.11 · White Friday
A11: Actual mix this month
A12: Code | B12: Pillar | C12: Posts | D12: Share
A13: ONE | B13: One Call | C13: =COUNTIF(Calendar!$G:$G,B13) -> 18 | D13: =IF(SUM($C$13:$C$17)=0,0,C13/SUM($C$13:$C$17)) -> 0.16216216
A14: KNOW | B14: Know Before You Go | C14: =COUNTIF(Calendar!$G:$G,B14) -> 18 | D14: =IF(SUM($C$13:$C$17)=0,0,C14/SUM($C$13:$C$17)) -> 0.16216216
A15: HOR | B15: Horizons | C15: =COUNTIF(Calendar!$G:$G,B15) -> 40 | D15: =IF(SUM($C$13:$C$17)=0,0,C15/SUM($C$13:$C$17)) -> 0.36036036
A16: BIZ | B16: Events & Business | C16: =COUNTIF(Calendar!$G:$G,B16) -> 12 | D16: =IF(SUM($C$13:$C$17)=0,0,C16/SUM($C$13:$C$17)) -> 0.10810811
A17: MOM | B17: Moments & Offers | C17: =COUNTIF(Calendar!$G:$G,B17) -> 23 | D17: =IF(SUM($C$13:$C$17)=0,0,C17/SUM($C$13:$C$17)) -> 0.20720721
A20: Recurring series
A21: Series | B21: Where | C21: How often | D21: Format
A22: One Call / مكالمة وحدة | B22: IG Reel, then TikTok | C22: Every 2 weeks | D22: Split screen: the client's voice note on the left, the concierge solving it on the right, a timer. Ends on the client's reply. The signature format.
A23: Visa in 60 / الفيزا بدقيقة | B23: TikTok, IG, X thread | C23: Weekly | D23: A concierge explains one visa topic in 60 seconds. Keyword spoken in the first 3 seconds. The best search driver.
A24: Weekend Radar / رادار الويكند | B24: IG carousel, X thread | C24: Every Thursday 19:30 | D24: What's on this weekend in Riyadh and nearby, with one tip per event. A habit-forming, save-and-share format.
A25: Concierge Confessions / من دفتر الكونسيرج | B25: IG Reel | C25: Every 2 weeks | D25: Storytime about a real (anonymised) case. Calm, human, a little funny.
A26: Behind the Curtain / خلف الستارة | B26: IG Reel, TikTok | C26: Every 2 weeks | D26: Event builds, show-caller POV, crew. The craft gap among event companies.
A27: Europe in Winter / شتاء أوروبا | B27: IG Reel, TikTok, X | C27: Weekly in Nov-Jan | D27: Winter markets, visas and itineraries for the mid-year break.
A28: Field Notes | B28: LinkedIn document | C28: Weekly | D28: One practical B2B lesson: timelines, checklists, policy clauses.
A29: Horizon Keepers | B29: LinkedIn + IG Story | C29: Monthly | D29: A team member spotlight. The people behind the plan.
A30: Umrah, Step by Step / العمرة خطوة بخطوة | B30: TikTok, IG | C30: Weekly from 29 Nov | D30: Calm, respectful explainers ahead of Rajab and Ramadan. No music, no hard sell.

Sheet Guidelines
A1: Brand voice, design and profile guidelines
A4: Voice & copy | B4: Guideline
A5: We sound like | B5: A calm, capable host who has already thought of it. Warm, short, specific. Saudi dialect on TikTok and X, polished Arabic on IG, clear English on LinkedIn.
A6: We say | B6: 'Say it once. We'll take it from there.' · 'One call. Everything moves.' · 'Every horizon, within reach.' · كل أفق، في متناولك · قلها مرة… والباقي علينا
A7: We never | B7: Flex wealth or price tags (GAMR rules, Sep 2025) · joke about airports, flights or safety · promise visa approvals · use clickbait we can't back up · mock anyone · post children's faces or domestic workers
A8: Hooks that work | B8: A number + a promise ('5 things nobody tells you…') · a POV · a question the viewer has asked themselves ('Schengen for 5 years?') · a sound-first ASMR open · a relatable moment ('Last day before the break')
A9: Captions | B9: Line 1 = the keyword + the hook. 2-4 short lines. One CTA. Emojis as punctuation, max 3. Arabic first, English after a line break on IG.
A10: CTAs (rotate) | B10: Save it · Send it to your travel buddy · Comment your destination · WhatsApp '11' / '🤍' / 'عمرة' · Tag who you're taking
A12: Design | B12: Guideline
A13: Colours | B13: Brand green #1E352D (backgrounds) · Sand #E9E2D8 (light backgrounds) · Gold #D9B77A (accents, numbers, one highlight per post) · Ink #0F1A16. One accent per design.
A14: Type | B14: Latin: Inter Tight (headlines, tight tracking) + Instrument Serif italic (one emphasised word). Arabic: IBM Plex Sans Arabic (body) + Reem Kufi (display words). Aref Ruqaa for signatures and quotes only.
A15: Poster text | B15: Max 7 words in the headline. One idea per slide. Arabic headline larger than English. Min 48px body text at 1080 wide.
A16: Logo | B16: The symbol (sun) bottom-centre or bottom-right on statics, small. Full logo only on cover slides and end cards. Never on Reels' first frame.
... A29: Saturday | B29: Client stories: reshare tagged trips (with permission) + a 'where to next?' sticker.
A31: Profile | B31: Display name | C31: Bio | D31: Note
A32: Instagram | B32: مادا | Mada Trips | C32: سفر · فنادق · تأشيرات · فعاليات من الرياض ✈️ قلها مرة… والباقي علينا Travel · Visas · Events · Riyadh 👇 واتساب | D32: Name field carries keywords: 'مادا للسفر | Mada Trips Riyadh'
A33: TikTok | B33: مادا للسفر | C33: نخطط لك السفر والفيزا والفعاليات 🇸🇦 قلها مرة… والباقي علينا 👇 | D33: Username: @madatrips (secure the same handle everywhere)
A34: X | B34: مادا | Mada Trips | C34: سفر، تذاكر، فنادق، تأشيرات، فعاليات، كوادر وتقنية. من الرياض لكل أفق. واتساب ‎+966 56 668 2662 | D34: Pin the launch post, then the current offer
A35: LinkedIn | B35: Mada Trips | C35: One partner for everything that moves: corporate travel, delegations, events, manpower, specialist supply and IT. Riyadh, KSA. | D35: Tagline + the 9 services under 'Specialties' for search

Sheet Keywords
A1: Keyword bank (search on TikTok, Instagram and Google)
A4: • Search volumes for Arabic terms weren't available. Validate every cluster before posting: TikTok search autocomplete + 'Others searched for', TikTok Creative Center (region: Saudi Arabia) and Google Trends (geo: SA).
A5: • Use one main keyword per post in four places: spoken in the first 3 seconds, on screen, in caption line 1, and in 1-2 of the 5 hashtags.
A6: • Spell it the way people search, which is often colloquial: 'وش اسوي بالرياض', not formal Arabic.
A7: • Put keywords in the profile name field too (e.g. 'مادا للسفر | Mada Trips Riyadh').
A9: Cluster | B9: Arabic keywords | C9: English keywords
A10: Visas | B10: تأشيرة شنغن · فيزا شنغن للسعوديين · شنغن ٥ سنوات · مواعيد السفارة · اوراق الفيزا · ETA بريطانيا · فيزا امريكا · بدون فيزا للسعوديين | C10: Schengen visa Saudi · UK ETA Saudi · US visa Riyadh
A11: Breaks & deals | B11: اجازة الخريف · وين نسافر في الاجازة · رحلات قريبة من الرياض · عروض سفر · عروض طيران · باقات سياحية · الجمعة البيضاء عروض سفر | C11: autumn break Saudi · White Friday travel deals
A12: Domestic | B12: العلا · سماء العلا · منطاد العلا · برنامج العلا ٣ ايام · ابها والسودة · البحر الاحمر · الدرعية · كشتة · مخيمات الرياض · حافة العالم | C12: things to do in AlUla · AlUla Skies · Red Sea resorts · desert camping Riyadh
A13: Riyadh Season | B13: موسم الرياض ٢٠٢٦ · بوليفارد وورلد · فعاليات الرياض هالويكند · وش اسوي بالرياض · موسم الرياض للعائلات | C13: Riyadh Season 2026 · Riyadh this weekend
A14: Abroad | B14: سفر اوروبا شتاء · فيينا في الشتاء · لندن في الشتاء · جورجيا في الشتاء · مسقط سياحة · باكو · تبليسي | C14: Europe winter trip · Vienna Christmas market · Winter Wonderland London
A15: Umrah | B15: باقات عمرة · عمرة رجب · عمرة رمضان · تصريح عمرة نسك · فنادق قريبة من الحرم | C15: Umrah package from Riyadh · Umrah permit Nusuk
A16: B2B (LinkedIn) | B16: تنظيم فعاليات الرياض · توريد عمالة · خدمات الأعمال | C16: corporate travel Saudi Arabia · event management Riyadh · MICE Saudi Arabia · manpower supply KSA · delegation management

Sheet Competitors
A1: Competitor analysis
A2: Follower counts are approximate. Instagram and TikTok analytics are login-gated, so verify by hand before quoting.
A4: Brand | B4: Handles | C4: Size (approx.) | D4: Style | E4: What wins | F4: Gap for Mada
A5: Almosafer (Seera) | B5: @almosafer · @almosafertravel_sa | C5: ~154K IG on the regional account (HypeAuditor); main accounts larger | D5: Polished, family, mostly Modern Standard Arabic. Deals, seasonal moments, rare emotional brand films. | E5: 'Stories of Mecca' (87M organic views), 'As Far As We Go' (8M views in a week). | F5: Transactional day to day. No human advisor on camera. No B2B voice.
A6: Wego / Flyin / Rehlat | B6: @wego_arabic · @flyin · @rehlat | C6: Unverified (likely hundreds of thousands) | D6: Bright, promotional, price hacks and app promos. | E6: Price authority, 'cheapest time to fly' content. | F6: Commoditised and interchangeable. No premium tier, little Umrah depth.
A7: Saudia | B7: @saudi_airlines | C7: Very large on X (unverified) | D7: Institutional. Product-as-campaign. | E7: Cannes Lions 2026: 'Let It Fly' (39K stickers redeemed in 22 countries), 'The Coolest Ihram' (237M impressions). | F7: X is mostly complaints. Impersonal. Lesson: a celebrity who doesn't fit the culture can backfire.
A8: flynas | B8: @flynas | C8: Unverified | D8: Friendly, value-led, creator-powered. | E8: 'People's Lens': creators produce Saudi destination content in exchange for flights. | F8: Low-cost image.
A9: Riyadh Air | B9: @riyadhair | C9: Large, built before the first flight (unverified) | D9: Premium, bilingual, cinematic. The CEO and employees as faces. | E9: TikTok Ad Awards 2025 'Best of Visionary Marketing'. Built anticipation from zero. | F9: Aspirational, not service. The benchmark for a new brand: craft + people + anticipation.
A10: Visit Saudi · AlUla · Riyadh Season | B10: @visitsaudi · @experiencealula · @riyadhseason | C10: Very large (government) | D10: Glossy, celebrities, cinematic places, hype announcements. | E10: Visit Saudi's TikTok Branded Search Hub (18M interactions). Riyadh Season's viral launch films. | F10: They create demand but never answer 'how do I do this easily?'. Mada converts their demand.
A11: MDLBEAST | B11: @mdlbeast | C11: +29.7K followers in one Soundstorm cycle | D11: Youth, real-time hype, BTS, English with slang. | E11: Soundstorm 2024: 42.3M reach. 'Inner Sounds' TikTok effect. | F11: Niche audience. Soundstorm 2026 is cancelled.
A12: Corporate event & manpower firms (Sela, Pico, Maharah…) | B12: LinkedIn-first | C12: Maharah ~71K on LinkedIn | D12: 'Proud to have delivered…' posts, milestones, portfolio grids. | E12: Credentials and scale. | F12: Nobody teaches. Nobody shows the craft. Nobody bundles event + travel + visas for delegates.
A13: Global benchmarks | B13: Ryanair · Booking.com · Emirates · Qatar Airways | C13: Millions | D13: Ryanair: speed and trend-native meme. Booking: always-on trend team + micro-creators as producers. Emirates: hero product. | E13: Speed, native formats, creators as production. | F13: Copy the speed, not Ryanair's tone, which is off-brand for premium.
A15: White space for Mada | B15: How we take it
A16: A face and a phone number | B16: Recurring concierges on camera (One Call, Concierge Confessions, Day in the Life). No Saudi OTA does this.
A17: The how, not just the wow | B17: Visit Saudi and Riyadh Season sell the dream. We show how it happens effortlessly: tickets, transfers, the 2am rebooking.
A18: From hype to here | B18: When a big event drops, post a same-day 'how to go, properly' piece within 24 hours.
A19: Umrah with dignity | B19: Calm, educational, respectful Umrah content. Competitors are either flyer-like or institutional.
A20: A B2B teacher | B20: Field Notes on LinkedIn: delegations, MICE, manpower steps. Corporate peers only post milestones.
A21: The Horizon Card | B21: A small signature gesture (a calligraphy welcome card, an elders' travel kit) that becomes shareable content, at a boutique scale like Saudia's product-as-campaign ideas.
A22: Snapchat (recommended) | B22: Snapchat reaches 89% of Saudi adults (25.3M). It isn't in the brief, but secure @madatrips and repost vertical videos there at minimum.

Sheet Moments
A1: Moments calendar: Nov 2026 with Dec-Feb teasers
A4: Date | B4: Moment | C4: Where | D4: How we use it | E4: Status
A5: 21 Oct - end Dec | B5: Riyadh Season 2026 'Big Time' (Boulevard World, Boulevard City, Wonder Garden, The Groves, Farmers' Market, Ana Arabia @ VIA Riyadh) | C5: Riyadh | D5: Weekend Radar anchor all month | E5: Confirmed
A6: 26-29 Oct | B6: FII10, 'The Power of Legacy' | C6: KAICC Riyadh | D6: LinkedIn delegate checklist (3 Nov) | E6: Confirmed
A7: 3 Nov | B7: British Airways' planned limited Riyadh restart | C7: RUH | D7: Only confirmed route updates | E7: Planned
A8: 6-15 Nov | B8: AlUla Skies Festival: balloons, glow shows, stargazing | C8: AlUla | D8: Top domestic trip of the month | E8: Confirmed
A9: 7 Nov | B9: WWE Crown Jewel | C9: Riyadh Season Stadium, KAFD | D9: Event-night tips, atmosphere | E9: Confirmed
A10: 7-12 Nov | B10: Moonless skies (new moon 9 Nov) | C10: Desert / AlUla | D10: Stargazing content | E10: Astronomical
A11: 11 Nov | B11: 11.11 Singles Day · ~1 Jumada al-Akhirah 1448 | C11: Online | D11: 11 upgrades offer | E11: Confirmed
A12: 13 Nov | B12: World Kindness Day | C12: Global | D12: Horizon Card launch | E12: Confirmed
A13: 15 Nov | B13: Leonid meteor shower peak | C13: Desert | D13: Night-sky Reels | E13: Astronomical
A14: 16 Nov | B14: International Day for Tolerance | C14: Global | D14: Saudi hospitality guide | E14: Confirmed
A15: 16-19 Nov | B15: Cityscape Global 2026 (12:00-22:00, 18+) | C15: RECC Malham | D15: B2B logistics | E15: Confirmed
... A30: ~8 Feb 2027 | B30: Ramadan 1448 | C30: KSA | D30: Umrah, book early | E30: Expected
A32: Cancelled / moved / unconfirmed: don't promote
A33: • Red Sea International Film Festival 2026 (postponed to Q4 2027)
A34: • MDLBEAST Soundstorm 2026 (cancelled)
A35: • Formula E Diriyah (moved to Jeddah, 18-19 Dec)
A36: • Riyadh Comedy Festival (no 2026 edition announced)
A37: • Joy Awards 2027 (reported cancelled, not yet official)
A38: • Noor Riyadh, Winter at Tantora, Jeddah & Diriyah Seasons: 2026 dates not announced

Sheet KPIs & tracking
A1: KPIs and tracking
A2: Targets for month one, set against published benchmarks. The live columns read the Calendar results.
A4: KPI | B4: Month-1 target | C4: Benchmark / why
A5: Instagram engagement rate (by followers) | B5: ≥ 1.0% | C5: Travel & hospitality averages 0.4% (Dash Social, H2 2025). All-industry 0.45-0.48% (Socialinsider 2026).
A6: Instagram saves + sends per reach | B6: ≥ 3% on carousels | C6: Instagram ranks on sends per reach and watch time (Mosseri, Jan 2025).
A7: TikTok engagement rate | B7: ≥ 4% | C7: Travel averages 3.5% (Dash Social, H2 2025).
A8: TikTok 3-second hold | B8: ≥ 35% | C8: 20-35% is average, 35-50% good (vendor benchmark).
A9: Average watch % (Reels/TikTok) | B9: ≥ 50% on videos under 30s | C9: Track per hook style. Kill hooks that fall below 30%.
A10: X engagement rate | B10: ≥ 0.3% | C10: Platform average 0.10% (Socialinsider, Jan 2026).
A11: LinkedIn engagement (by impressions) | B11: ≥ 5% | C11: Documents 5.85-6.10% (Socialinsider 2025).
A12: WhatsApp conversations from social | B12: Track weekly | C12: Ask 'Where did you find us?' in the first WhatsApp reply. Keyword CTAs ('11', '🤍', 'عمرة') make it measurable.
A13: Search appearances | B13: Rank top 10 for 5 target terms | C13: Check TikTok search weekly for: تأشيرة شنغن, إجازة الخريف, العلا نوفمبر, رادار الويكند, باقات عمرة.
A14: Response time | B14: < 1 hour (09:00-23:00) | C14: Comments and DMs.
A17: Live results by platform (from Calendar)
A18: Platform | B18: Posts planned | C18: Posted | D18: Total reach | E18: Avg eng. rate (posted) | F18: Total saves | G18: Total shares
A19: Instagram | B19: =COUNTIF(Calendar!$E:$E,A19) -> 35 | C19: =COUNTIFS(Calendar!$E:$E,A19,Calendar!$V:$V,"Posted") -> 0 | D19: =SUMIF(Calendar!$E:$E,A19,Calendar!$W:$W) -> 0 | E19: =IFERROR(AVERAGEIFS(Calendar!$AC:$AC,Calendar!$E:$E,A19,Calendar!$V:$V,"Posted"),"") | F19: =SUMIF(Calendar!$E:$E,A19,Calendar!$AB:$AB) -> 0 | G19: =SUMIF(Calendar!$E:$E,A19,Calendar!$AA:$AA) -> 0
A20: TikTok | B20: =COUNTIF(Calendar!$E:$E,A20) -> 34 | C20: =COUNTIFS(Calendar!$E:$E,A20,Calendar!$V:$V,"Posted") -> 0 | D20: =SUMIF(Calendar!$E:$E,A20,Calendar!$W:$W) -> 0 | E20: =IFERROR(AVERAGEIFS(Calendar!$AC:$AC,Calendar!$E:$E,A20,Calendar!$V:$V,"Posted"),"") | F20: =SUMIF(Calendar!$E:$E,A20,Calendar!$AB:$AB) -> 0 | G20: =SUMIF(Calendar!$E:$E,A20,Calendar!$AA:$AA) -> 0
A21: X | B21: =COUNTIF(Calendar!$E:$E,A21) -> 30 | C21: =COUNTIFS(Calendar!$E:$E,A21,Calendar!$V:$V,"Posted") -> 0 | D21: =SUMIF(Calendar!$E:$E,A21,Calendar!$W:$W) -> 0 | E21: =IFERROR(AVERAGEIFS(Calendar!$AC:$AC,Calendar!$E:$E,A21,Calendar!$V:$V,"Posted"),"") | F21: =SUMIF(Calendar!$E:$E,A21,Calendar!$AB:$AB) -> 0 | G21: =SUMIF(Calendar!$E:$E,A21,Calendar!$AA:$AA) -> 0
A22: LinkedIn | B22: =COUNTIF(Calendar!$E:$E,A22) -> 12 | C22: =COUNTIFS(Calendar!$E:$E,A22,Calendar!$V:$V,"Posted") -> 0 | D22: =SUMIF(Calendar!$E:$E,A22,Calendar!$W:$W) -> 0 | E22: =IFERROR(AVERAGEIFS(Calendar!$AC:$AC,Calendar!$E:$E,A22,Calendar!$V:$V,"Posted"),"") | F22: =SUMIF(Calendar!$E:$E,A22,Calendar!$AB:$AB) -> 0 | G22: =SUMIF(Calendar!$E:$E,A22,Calendar!$AA:$AA) -> 0

Sheet Workflow & sensitivity
A1: Weekly workflow and sensitivity protocol
A4: When | B4: What
A5: Sunday | B5: Weekly planning: check the moments (events, airline news, weather), finalise the week's copy, sign-off by the brand lead.
A6: Monday + Wednesday | B6: Shoot days: batch 4-6 videos per session (concierge explainers, One Call, BTS). Use a script template with the hook, 3 beats and the CTA.
A7: Tuesday + Thursday | B7: Edit + design: templates in Canva/Figma/CapCut. Arabic proofreading by a native speaker before scheduling.
A8: Daily 09:00 | B8: Check the sensitivity protocol and news, then publish. 60 minutes of community replies after every post.
A9: Thursday | B9: Weekly report: top 3 and bottom 3 posts, hook hold rates, saves, WhatsApp leads. Turn one winner into a second version next week.
A10: Approvals | B10: Offers (11.11, White Friday, the LinkedIn Q1 offer) need management. The founder quote needs Bader. Visa and Umrah facts need an ops check. Paid creators need a Mawthooq licence.
A12: Sensitivity protocol
A13: 1 | B13: Every morning check the news for regional security, airport status and airline suspensions. If there's an incident: pause all scheduled posts within 30 minutes, post nothing promotional for 24-48 hours, and keep only helpful, factual posts (e.g. the 'disruption help line').
A14: 2 | B14: Never joke about airports, flights or safety. Never use footage of RUH in the coming weeks.
A15: 3 | B15: Never claim an airline or route is operating unless the airline has confirmed it. Link to the airline's own announcement in DMs.
A16: 4 | B16: Visas and Umrah: say 'up to', 'at the embassy's discretion', 'expected (moon sighting)'. Never promise approval.
A17: 5 | B17: GAMR content rules (Sep 2025): no flaunting wealth, modest dress, no children or domestic workers in lifestyle content, no mockery, no tribal or sectarian content.
A18: 6 | B18: Paid creators must hold a Mawthooq licence (SAR 15,000 for 3 years). Mark paid content as an ad (#إعلان). Our own account promoting our own services is exempt.
A19: 7 | B19: Discounts: follow Ministry of Commerce rules on sales claims (no fake 'was/now' prices). Real terms on every offer.
A20: 8 | B20: Re-check every event date the week of posting. Several were moved or cancelled this season.

Sheet Sources
A1: Sources
A2: Research compiled 18 Oct 2026. Vendor benchmarks use different methods, so only compare figures from the same source.
A4: Source | B4: URL
A5: DataReportal: Digital 2026 Saudi Arabia | B5: https://datareportal.com/reports/digital-2026-saudi-arabia
A6: CST: Saudi Internet Report 2025 | B6: https://www.cst.gov.sa/en/media-center/news/N2026071901
A7: AGBI: Gulf's love for Arabic content (Feb 2026) | B7: https://www.agbi.com/analysis/media/2026/02/gulfs-love-for-arabic-content-shields-local-tiktok
A8: Social Media Today: Instagram algorithm insights (Jan 2025) | B8: https://www.socialmediatoday.com/news/instagram-shares-algorithm-insights-2025/738034/
A9: Tubefilter: Instagram originality enforcement (30 Apr 2026) | B9: https://tubefilter.com/2026/04/30/instagram-removes-algorithm-recommendations-repost-content-aggregator
A10: Engadget: 3-minute Reels & 3:4 grid (Jan 2025) | B10: https://www.engadget.com/social-media/instagram-swoops-in-with-3-minute-reels-and-rectangular-profile-grids-as-the-tiktok-ban-gets-real-201316339.html
A11: Instagram 5-hashtag cap (Dec 2025) | B11: https://inmagic.ai/how-many-hashtags-on-instagram/
A12: Buffer: best content formats 2026 | B12: https://buffer.com/resources/data-best-content-format-social-media/
A13: Buffer: how often to post on Instagram | B13: https://buffer.com/resources/how-often-to-post-on-instagram/
A14: Socialinsider: 2026 benchmarks | B14: https://www.socialinsider.io/social-media-benchmarks
A15: Socialinsider: X benchmarks (Jan 2026) | B15: https://www.socialinsider.io/blog/twitter-benchmarks/
... A49: DJ Mag: Soundstorm 2026 cancelled | B49: https://djmag.com/news/soundstorm-festival-cancels-2026-edition
